Workbook

Sheet BD Strategy v2
A1: Singapore Headhunting BD Target List v2 — Data Eng · AI Governance · AI Security · AI Risk · Software Eng
A2: Expanded Oct 2026 from v1 (original sheets kept at the back unchanged). Company-level research from public sources; no personal data scraped.
A4: What changed in v2
A5: • Master list now covers 222 accounts (v1: 60 kept/merged, v2: 79 new, v2.1: 83 added by splitting grouped rows into individual companies), all in one filterable sheet with role flags for 5 directions.
A6: • v2.1: every grouped row (e.g. 'Chinese credit-tech going abroad', Chinese bank branches, quant funds, wallets, robotics, handset makers, IT vendors, MindForge members, public sector) is now one row per company. Each split row says which group it came from in 'v2 Update / Correction'. New finds: Lingjun (灵均) SG office, SUNRATE, TrustDecision (同盾), OneConnect (金融壹账通), Kuaishou's SG unit, PixVerse, China Life SG, DCITS, Sunline, XTransfer's MAS licence.
A7: • Wider definition of 'Chinese-connected' (China Link A–E): not only Chinese-HQ firms, but SG-relocated Chinese startups, Greater-China/diaspora founders, and non-Chinese firms with China-origin tech leaders or TA (type D — verify on LinkedIn).
A8: • Added AI Security and AI Risk as directions, plus general Software Engineering. Companies are included if a need is plausible, not only if a role is posted today.
A9: • Corrections to v1: PingPong ≠ 连连数字 (LianLian is a separate company, added); Binance has no MAS licence and exited SG retail in 2021 (verify roles); Haitong International merged into Guotai Haitong; MiniMax and Zhipu upgraded — SG entities now confirmed.
A11: Why now — new signals since v1
A12: 1. Chinese AI companies keep moving to SG ('Singapore-washing'): Manus (→ Meta), MiroMind/Shanda (AGI research exclusively in SG from Jan 2026), Tabcut, Plaud (APAC HQ opened 16 Sep 2026, 100→150 staff). Beijing is now scrutinising these moves (Manus deal review) — relocating teams face backfill gaps for staff who won't move.
A13: 2. MAS AI Risk Management Guidelines (7 Oct 2026) apply to ALL regulated FIs — including Chinese bank branches, Chinese online brokers (Moomoo/Futu, Tiger), digital banks (ANEXT, Green Link, MariBank, GXS) and crypto/payment licensees. Their China HQs often don't know the requirement → you can bring both the regulation insight and the talent.
A14: 3. Chinese giants are running an AI-talent war in SG (campus recruiting at NUS/NTU by Huawei, Alibaba, ByteDance, Trip.com, MiniMax in 2026) — lateral hiring budgets follow.
... A32: Public sources incl. MAS (7 Oct 2026), EDB (Plaud, Sep 2026), SCMP (MiroMind Jan 2026; Manus 2025), Bloomberg (ByteDance Seed Feb 2026; WeRide/Pony Sep 2025), e27 (OneByZero Oct 2026), KrASIA (Ropedia), HCAmag/People Matters (campus AI hiring 2026), company sites and filings. Founder backgrounds for some startups are marked 'verify' — do not rely on names alone; confirm on LinkedIn. All signals are a snapshot as of 8 Oct 2026.

Sheet LinkedIn Setup Guide
A1: LinkedIn Recruiter setup — step by step
A3: 1. PROJECTS
A4: Create 3 projects | B4: 'BD-W1 High' (40 companies) · 'BD-W2 Medium' (93) · 'BD-W3 Long-tail' (71). Project = column E in 'LinkedIn Search Plan'. Mark them as BD / client development (not a job) so they don't mix with candidate pipelines.
A5: Pipeline stages | B5: Rename the stages to: Uncontacted → InMail sent → Replied → Meeting → Proposal / terms → Client (signed) → Not now.
A6: Tags | B6: Create tags so you can filter across projects: Persona (HM / TA / Founder), Direction (DE / AIGov / AISec / AIRisk / SWE), China Link (A-E), Lang (CN / EN).
A7: 2. FIND PEOPLE
A8: Per company | B8: Search → Current company = column C (pick the exact company page in the dropdown) + Location = Singapore. Paste column F into Job titles (Boolean) for hiring managers, then repeat with column G for TA/HR (and column H for startup founders).
A9: Who to save (2-4 per company) | B9: 1 hiring manager in your direction (Head of Data / AI governance / security / risk / Eng), 1 senior leader (CTO / CRO / CDO), 1 TA/HR contact. For startups (<50 staff), the founder or CTO alone is enough.
A10: Spotlights for Chinese-speaking contacts | B10: In Recruiter's spotlight / filters: Spoken languages = Chinese; Schools = Tsinghua, Peking, Zhejiang, SJTU, Fudan, USTC; Past company = ByteDance, Alibaba, Tencent, Huawei. Use these to choose the CN or EN template.
A11: Before saving | B11: For rows marked [verify SG team first], check the company page and its SG job posts. If it has no SG staff, mark the row Dead and skip it.
A12: 3. MESSAGING
A13: Save the templates | B13: Create each template in the 'InMail Templates' sheet in Recruiter, then swap {firstName} / {company} / {senderFirstName} for Recruiter's Insert variables.
A14: Pick the template | B14: Column J = suggested first message. Use the T6 (TA/HR) template for TA/HR contacts. Always rewrite the [signal] line using the 'BD Signal / Why Now' column of the Master list.
A15: Cadence | B15: Day 0 InMail → day 5-7 F1 (with a data point or anonymised profile) → day 14 F2 (close the loop). Message no more than 2 people per company in the same week.
A16: InMail budget | B16: About 120 InMails for Wave 1 (3 people × 40 companies). Recruiter Lite has far fewer monthly credits than Recruiter Corporate, so check your seat. Save InMails for hiring managers, and use connection requests with a note (≤300 characters) or free messages to Open Profiles for the rest.
A17: Track | B17: Update 'LinkedIn Search Plan' columns L-N and the Master list's BD Status; the Summary sheet counts the pipeline automatically.
A18: 4. COMPLIANCE
A19: Data | B19: Keep contact details inside LinkedIn and your own ATS/CRM. Don't export profiles in bulk; respect LinkedIn's terms and Singapore's PDPA.

Sheet Master Target List
A1: Master BD Target List (Singapore) — Data Eng · AI Governance · AI Security · AI Risk · Software Eng
A2: China Link: A = Chinese HQ/SOE · B = Chinese-founded, HQ'd/relocated to SG · C = Greater-China / Chinese-diaspora founders · D = non-Chinese firm with China-origin tech leaders/TA (verify) · E = role fit only. Role columns: ● = core need, ○ = likely/possible. Yellow columns (BD Status, Next Step) are yours to fill in.
A4: # | B4: Company | C4: Chinese Name | D4: Category | E4: China Link | F4: China Link Detail | G4: Data Eng | H4: AI Gov | I4: AI Security | J4: AI Risk | K4: SWE | L4: Size / Stage | M4: BD Signal / Why Now | N4: Suggested BD Angle | O4: Priority | P4: Confidence | Q4: Source | R4: Origin | S4: v2 Update / Correction | T4: BD Status | U4: Next Step / Notes
A5: 1 | B5: Plaud | C5: Plaud.ai | D5: AI Startups & Labs (Chinese-founded / SG-relocated) | E5: B | F5: Chinese-founded AI hardware/agent company; Singapore is its APAC HQ and first R&D hub outside HQ | G5: ● | H5: ○ | K5: ● | L5: Scale-up; SG team ~10 → ~100 in 9 months, target 150 | M5: Opened 15,000 sq ft APAC HQ at MBFC on 16 Sep 2026; doubled SG investment to ≥S$20M; actively hiring AI engineers, AI agent architects, data scientists for its first overseas R&D hub | N5: Hottest Chinese-founded AI hiring signal in SG right now — team is 2/3 of the way to its 150 target, TA is stretched; pitch AI/agent engineers + data scientists, Mandarin-speaking HQ liaison | O5: High | P5: Confirmed | Q5: EDB press release (Sep 2026); HRO / TechCoffeeHouse Jun & Sep 2026 | R5: v2 new | T5: Not started
A6: 2 | B6: MiroMind (Shanda Group) | C6: 盛大 MiroMind | D6: AI Startups & Labs (Chinese-founded / SG-relocated) | E6: B | F6: Backed by Shanda (Chen Tianqiao); Jan 2026 reorg made Singapore the exclusive base for its AGI research; Shanghai staff asked to relocate | G6: ○ | I6: ● | K6: ● | L6: Research lab; >80% PhD team (per public posts) | M6: Jan 2026: AGI / fundamental research to be done exclusively in Singapore; careers page hiring engineers for a SG-based team; a 'Verifiable AI Lab' is being set up | N6: Relocation = backfill gap for staff who won't move from Shanghai; pitch research engineers, LLM infra, and AI safety / verification profiles | O6: High | P6: Confirmed | Q6: SCMP Jan 2026; miromind.ai careers / announcement | R6: v2 new | T6: Not started
A7: 3 | B7: Ropedia | C7: Ropedia | D7: AI Startups & Labs (Chinese-founded / SG-relocated) | E7: C | F7: SG-based physical-AI data infrastructure; co-founders Zhaoxi Chen & Fangzhou Hong (verify background on LinkedIn) | G7: ● | K7: ● | L7: Pre-Series A US$22M | M7: Large pre-A round for a data-infra startup → immediate engineering build-out | N7: Data infra is literally the product — your strongest Data Engineer pitch; reach out to founders directly | O7: High | P7: Confirmed | Q7: KrASIA 'Deals in brief' 2026 | R7: v2 new | T7: Not started
A8: 4 | B8: OneByZero (OBZ) | C8: OneByZero | D8: AI Startups & Labs (Chinese-founded / SG-relocated) | E8: E | F8: SG-based enterprise AI deployment firm (founders' background to verify) | G8: ● | H8: ● | K8: ● | L8: Series A US$20M (Oct 2026, Jungle Ventures) | M8: Raised 5 Oct 2026 to expand APAC + enter Japan — hiring burst imminent | N8: Call this week: funding is 3 days old. Pitch forward-deployed engineers, data engineers, AI governance (enterprise rollout) | O8: High | P8: Confirmed | Q8: e27, 5 Oct 2026 | R8: v2 new | T8: Not started
A9: 5 | B9: Manus (Butterfly Effect) — now Meta | C9: 蝴蝶效应 Manus | D9: AI Startups & Labs (Chinese-founded / SG-relocated) | E9: B | F9: Founded in China (Xiao Hong); moved HQ to Singapore mid-2025; acquired by Meta (~US$2B); deal under Chinese regulatory review in 2026 | G9: ○ | I9: ● | K9: ● | L9: Agent startup inside Meta; ~US$100M ARR before deal | M9: Laid off China staff and closed China offices when relocating; post-acquisition integration + China review = uncertain but active SG engineering base | N9: Dual use: (1) client for agent / infra / agent-security engineers if Meta keeps scaling SG; (2) rich candidate pool if integration causes attrition. Verify current SG headcount first | O9: Medium-High | P9: Confirmed | Q9: SCMP 2025; Wikipedia 'Manus (AI agent)'; Rest of World 2026 | R9: v2 new | T9: Not started
A10: 6 | B10: Genspark (MainFunc) | C10: Genspark | D10: AI Startups & Labs (Chinese-founded / SG-relocated) | E10: B | F10: Founded by ex-Baidu Xiaodu CEO/CTO (Eric Jing, Kay Zhu); offices in Palo Alto, Singapore, Japan; majority-Chinese team per commentary | G10: ● | I10: ○ | K10: ● | L10: Unicorn; Tencent invested | M10: Super-agent product scaling fast; SG is one of three offices | N10: Mandarin-speaking founders — ideal fit for your pitch; ask whether SG will host engineering vs. GTM only | O10: Medium-High | P10: Likely | Q10: The Information (Tencent investment); Crunchbase; AI Supremacy | R10: v2 new | T10: Not started
A11: 7 | B11: Simular | C11: Simular | D11: AI Startups & Labs (Chinese-founded / SG-relocated) | E11: C | F11: Computer-use agent startup; co-founders ex-Google DeepMind (reported as Ang Li & Jiachen Yang — verify) | I11: ● | K11: ● | L11: Venture-backed startup | M11: Jun 2026: hiring its FIRST dedicated security engineer in Singapore (agent attack surface) | N11: Textbook AI Security role — bring agent-security / appsec candidates; first hire usually wants agency help | O11: Medium-High | P11: Confirmed | Q11: Seedtable job listing (Jun 2026) | R11: v2 new | T11: Not started
A12: 8 | B12: Envision Digital | C12: 远景智能 | D12: AI Startups & Labs (Chinese-founded / SG-relocated) | E12: B | F12: Envision Group (Zhang Lei) AIoT / energy-AI arm, global HQ in Singapore | G12: ● | H12: ● | K12: ● | L12: Large, US$210M raised (Sequoia China, GIC) | M12: AIoT/energy-AI platform; SG global HQ with China R&D | N12: Mandarin-speaking leadership + SG HQ — pitch data platform engineers and AI governance for energy/critical infra | O12: Medium-High | P12: Confirmed | Q12: DealStreetAsia; company website | R12: v2 new | T12: Not started
A13: 9 | B13: Tabcut | C13: Tabcut | D13: AI Startups & Labs (Chinese-founded / SG-relocated) | E13: B | F13: Hangzhou founders moved global HQ to Singapore after raising from Kamet Capital | G13: ● | K13: ● | L13: Early-stage, US$5.6M raised | M13: TikTok-Shop analytics/data SaaS — data engineering is the product | N13: Small team without in-house TA; offer contingent search for data/backend engineers | O13: Medium | P13: Confirmed | Q13: Bloomberg / BusinessWorld 2024 (relocation report) | R13: v2 new | T13: Not started
A14: 10 | B14: Agnes AI (SapiensAI) | C14: Agnes AI | D14: AI Startups & Labs (Chinese-founded / SG-relocated) | E14: C | F14: SG-based, founded 2025 by Bruce Yang; positioned in Chinese media as part of Chinese-founder wave in SG ('DeepSeek of SEA') | G14: ● | I14: ○ | K14: ● | L14: Series A (Feb 2026) | M14: Post-Series A team build in SG | N14: Freshly funded, small team — fast decisions; verify founder network (Chinese-media coverage suggests Mandarin-speaking leadership) | O14: Medium | P14: Likely | Q14: Dealroom; TMTPost | R14: v2 new | T14: Not started
A15: 11 | B15: Sapient Intelligence | C15: Sapient Intelligence | D15: AI Startups & Labs (Chinese-founded / SG-relocated) | E15: B | F15: SG-based AGI research startup (HRM model); Chinese founding team (founder reported as Guan Wang — verify) | G15: ○ | K15: ● | L15: Early-stage research lab | M15: Gained global attention for Hierarchical Reasoning Model (2025); research hiring in SG | N15: Pitch research engineers / ML infra; small team, founder-led hiring | O15: Medium | P15: To verify | Q15: Public reporting 2025; verify current funding/headcount | R15: v2 new | T15: Not started
A16: 12 | B16: Skywork AI (Kunlun Tech) | C16: 昆仑万维 天工 | D16: AI Startups & Labs (Chinese-founded / SG-relocated) | E16: B | F16: Kunlun Tech's overseas AI apps published via Skywork AI Pte. Ltd. (Singapore) | G16: ● | H16: ○ | K16: ● | L16: Listed parent (Shenzhen), overseas AI app arm | M16: Overseas AI products (agents, music, short drama) operated from SG entity | N16: Verify engineering vs. ops split in SG; pitch AI product engineers + overseas compliance | O16: Medium | P16: To verify | Q16: App-store publisher records; public reporting | R16: v2 new | T16: Not started
A17: 13 | B17: WIZ.AI | C17: WIZ.AI | D17: AI Startups & Labs (Chinese-founded / SG-relocated) | E17: B | F17: SG conversational/voice-AI startup with Chinese founding team (founder reported as Jennifer Zhang — verify) | G17: ● | H17: ○ | K17: ● | L17: Series B-stage | M17: Voice-agent demand rising across SEA banks/telcos | N17: Pitch speech/LLM engineers; small TA team | O17: Medium | P17: Likely | Q17: Company website; Tech in Asia | R17: v2 new | T17: Not started
A18: 14 | B18: AI Rudder | C18: AI Rudder | D18: AI Startups & Labs (Chinese-founded / SG-relocated) | E18: C | F18: SG voice-AI collections/CS platform; founding team background to verify | G18: ● | K18: ● | L18: Growth-stage | M18: Voice AI for fintech collections across SEA | N18: Verify leadership; fintech clients also give AI Risk angle | O18: Low-Medium | P18: To verify | Q18: Company website | R18: v2 new | T18: Not started
A19: 15 | B19: Hypotenuse AI | C19: Hypotenuse AI | D19: AI Startups & Labs (Chinese-founded / SG-relocated) | E19: C | F19: SG GenAI content startup (YC), Singaporean-Chinese founder | K19: ● | L19: Early-stage | M19: Lean product/engineering team | N19: Small but founder-led hiring; good for 1-2 senior SWE placements | O19: Low | P19: Likely | Q19: e27 (YC-backed SG AI startups) | R19: v2 new | T19: Not started
A20: 16 | B20: SmartMore | C20: 思谋科技 | D20: AI Startups & Labs (Chinese-founded / SG-relocated) | E20: A | F20: Shenzhen industrial-AI company; reported plan to expand into SEA starting with Singapore | G20: ● | K20: ● | L20: Large Chinese AI unicorn | M20: Reported SEA expansion plan (date unclear) | N20: Radar — check for SG entity / job posts | O20: Radar | P20: To verify | Q20: Public reporting (undated) | R20: v2 new | T20: Not started
A21: 17 | B21: MiniMax | C21: MiniMax | D21: Chinese Foundation-Model Firms Going Abroad | E21: A | F21: HK-listed; SG subsidiaries Subsup Pte. Ltd. & Nanonoble Pte. Ltd. in group structure | G21: ● | H21: ● | K21: ● | L21: Unicorn, HK IPO early 2026 | M21: SG entities now confirmed in filings; recruiting AI talent at NUS/NTU (May 2026) | N21: Upgrade to High: entities + campus hiring confirmed; ask about SG compliance/trust & safety team | O21: High | P21: Confirmed | Q21: HK IPO filings; HCAmag May 2026 | R21: v2 new | S21: v2: replaces v1 row — SG subsidiaries now confirmed in IPO filings; upgraded to High | T21: Not started
A22: 18 | B22: ByteDance Seed (AI research) — Singapore lab | C22: 字节跳动 Seed | D22: Chinese Foundation-Model Firms Going Abroad | E22: A | F22: Seed has labs in US, Singapore and China; separate hiring team from TikTok | G22: ● | I22: ● | K22: ● | L22: Mega-scale AI lab | M22: Bloomberg Feb 2026: ~100 open roles in AI division; SG is one of three lab locations | N22: Treat as a separate account from TikTok — pitch research engineers, LLM infra, AI safety / red-team | O22: High | P22: Confirmed | Q22: Bloomberg 19 Feb 2026 | R22: v2 new | T22: Not started
A23: 19 | B23: Zhipu AI (Z.ai) | C23: 智谱 | D23: Chinese Foundation-Model Firms Going Abroad | E23: A | F23: Chinese 'AI Tiger'; VP confirmed Singapore office; SG entity (Jingsheng Hengxing Technology Pte.) in IPO structure | G23: ● | H23: ● | K23: ● | L23: Unicorn, listed / IPO stage | M23: Overseas offices in SG, Middle East, UK, Malaysia; sovereign-AI partnerships across SEA | N23: Upgrade from radar: SG office confirmed. Overseas compliance = AI Governance need; plus solutions/data engineers for SEA deals | O23: Medium-High | P23: Confirmed | Q23: GITEX Asia remarks (AOL/Reuters); IPO filings | R23: v2 new | S23: v2: replaces v1 radar row — SG office confirmed | T23: Not started
A24: 20 | B24: Kuaishou — Symphony Tech (SG unit) | C24: 快手 新加坡 | D24: Chinese Foundation-Model Firms Going Abroad | E24: A | F24: Kuaishou launched AI-companion app FantaSay via its Singapore unit Symphony Tech | G24: ● | H24: ● | I24: ● | K24: ● | L24: Mega-scale parent | M24: Overseas AI-companion app run from SG; content-safety scrutiny (NSFW reports) | N24: AI Gov / trust & safety + AI engineers — strong governance pitch given content concerns | O24: Medium | P24: Confirmed | Q24: Yahoo Finance / Bloomberg | R24: v2.1 | S24: v2.1: new | T24: Not started
A25: 21 | B25: PixVerse (AIsphere) | C25: 爱诗科技 | D25: Chinese Foundation-Model Firms Going Abroad | E25: B | F25: AI-video company; reportedly HQ Singapore with research in Beijing (verify — low-reliability source) | G25: ● | H25: ● | K25: ● | L25: Unicorn-stage | M25: Global AI-video product | N25: If SG HQ confirmed: AI engineers + content governance | O25: Medium | P25: To verify | Q25: Wiki / company directories | R25: v2.1 | S25: v2.1: new | T25: Not started
A26: 22 | B26: Moonshot AI (Kimi) | C26: 月之暗面 | D26: Chinese Foundation-Model Firms Going Abroad | E26: A | F26: Beijing; scaled back overseas consumer apps (2024); preparing HK IPO | H26: ● | L26: Unicorn | M26: No SG team found | N26: Radar | O26: Radar | P26: To verify | Q26: Yicai 2024; Wikipedia | R26: v2.1 | S26: v2.1: split from grouped row 'Moonshot / StepFun / AI Tigers' | T26: Not started
A27: 23 | B27: StepFun | C27: 阶跃星辰 | D27: Chinese Foundation-Model Firms Going Abroad | E27: A | F27: Shanghai AI Tiger | H27: ● | L27: Unicorn | M27: No SG team found | N27: Radar | O27: Radar | P27: To verify | Q27: — | R27: v2.1 | S27: v2.1: split from grouped row 'Moonshot / StepFun / AI Tigers' | T27: Not started
A28: 24 | B28: Baichuan AI | C28: 百川智能 | D28: Chinese Foundation-Model Firms Going Abroad | E28: A | F28: Beijing AI Tiger (healthcare focus) | H28: ● | L28: Unicorn | M28: No SG team found | N28: Radar | O28: Radar | P28: To verify | Q28: — | R28: v2.1 | S28: v2.1: split from grouped row 'Moonshot / StepFun / AI Tigers' | T28: Not started
A29: 25 | B29: 01.AI | C29: 零一万物 | D29: Chinese Foundation-Model Firms Going Abroad | E29: A | F29: Kai-Fu Lee's AI company | H29: ● | L29: Unicorn | M29: No SG team found | N29: Radar | O29: Radar | P29: To verify | Q29: — | R29: v2.1 | S29: v2.1: split from grouped row 'Moonshot / StepFun / AI Tigers' | T29: Not started
A30: 26 | B30: ByteDance / TikTok Singapore | C30: 字节跳动 / TikTok | D30: Tech Giants (Regional / Global HQ) | E30: A | F30: Chinese HQ; SG is global/APAC hub | G30: ● | H30: ● | I30: ○ | K30: ○ | L30: Mega-scale, aggressively expanding | M30: 2,353 of its ~10,000 2026 campus-recruitment roles are AI-related; Singapore is its global/APAC hub, and global data-compliance scrutiny makes both AI governance and data engineering talent urgently needed | N30: One of the top priority targets: high headcount volume, fast expansion, and "global regulatory scrutiny" is itself the strongest AI Governance pitch angle | O30: High | P30: Likely | Q30: 36kr / industry reporting synthesis | R30: v1 | S30: v2: ByteDance Seed, Lark, BytePlus added as separate accounts; also merged duplicate row from v1 DE sheet | T30: Not started
A31: 27 | B31: Alibaba Group / Alibaba Cloud International (Singapore) | C31: 阿里巴巴 | D31: Tech Giants (Regional / Global HQ) | E31: A | F31: Chinese HQ / mainland parent | G31: ● | H31: ● | I31: ○ | K31: ○ | L31: Mega-scale | M31: Alibaba Cloud has been headquartered in Singapore since 2015; AI-related roles make up 60-80% of Alibaba International's hiring | N31: A core buyer of data engineering talent — build separate contacts across its three business lines (Cloud / Ant / Lazada) | O31: High | P31: Likely | Q31: Industry reporting synthesis | R31: v1 | S31: v2: Ant International and Lazada split into their own rows | T31: Not started
A32: 28 | B32: Tencent Singapore | C32: 腾讯 | D32: Tech Giants (Regional / Global HQ) | E32: A | F32: Chinese HQ / mainland parent | G32: ● | I32: ○ | K32: ○ | L32: Large, intense AI talent war | M32: Offering 150% pay raises + 35% bonuses to attract AI talent, implying ample hiring budget and fast decision-making | N32: The high-pay signal supports a "precision top-candidate sourcing" pitch | O32: High | P32: Confirmed | Q32: Tom's Hardware reporting | R32: v1 | T32: Not started
A33: 29 | B33: Xiaomi Singapore | C33: 小米 | D33: Tech Giants (Regional / Global HQ) | E33: A | F33: Chinese HQ / mainland parent | G33: ● | I33: ○ | K33: ○ | L33: Large | M33: Indeed lists 178+ Data Engineer-related roles, spanning from Engineer level up to VP of Technology / Big Data Architect | N33: High volume across all seniority levels — good fit for a standing-search agreement | O33: High | P33: Confirmed | Q33: Indeed job listing statistics | R33: v1 | T33: Not started
A34: 30 | B34: SHEIN Singapore | C34: 希音 | D34: Tech Giants (Regional / Global HQ) | E34: B | F34: Chinese-founded; registered HQ in Singapore | G34: ● | I34: ○ | K34: ○ | L34: Mega-scale, HQ-level | M34: Registered HQ in Singapore (Robinson Road); supply chain, ad spend, and dynamic pricing all drive heavy data engineering demand | N34: Decision-making power sits locally in Singapore — one of the highest-value accounts to cultivate | O34: High | P34: Confirmed | Q34: Company website / craft.co | R34: v1 | T34: Not started
A35: 31 | B35: Grab | C35: Grab | D35: Tech Giants (Regional / Global HQ) | E35: D | F35: Large China-origin engineering population; historically had a Beijing R&D centre (verify current tech leads) | G35: ● | I35: ○ | K35: ○ | M35: Singapore R&D centre, 5,001-10,000 employees, continuous large-scale hiring | N35: SEA's largest super-app, large and high-turnover data teams — a good candidate for a long-term, steady client relationship | O35: High | P35: Confirmed | Q35: Glassdoor / Grab careers page | R35: v1 | T35: Not started
A36: 32 | B36: Ant International (Alipay+, Antom, WorldFirst, ANEXT Bank) | C36: 蚂蚁国际 | D36: Tech Giants (Regional / Global HQ) | E36: A | F36: Global HQ in Singapore; Chinese leadership | G36: ● | H36: ● | I36: ● | J36: ● | K36: ● | L36: Mega-scale; 4 business lines | M36: AI-heavy: Alipay+ Cockpit AI-as-a-Service, AI SHIELD fraud detection; ANEXT is an MAS-licensed digital wholesale bank → MAS AI Risk Guidelines apply | N36: Best single account for AI Risk + AI Security (fraud/deepfake/KYC) + AI Gov; split from 'Alibaba' row in v1 — build separate contacts per business line | O36: High | P36: Confirmed | Q36: Ant International press releases; EDB | R36: v2 new | T36: Not started
A37: 33 | B37: Sea / Shopee / Garena / MariBank | C37: 冬海集团 | D37: Tech Giants (Regional / Global HQ) | E37: C | F37: Founder & CEO Forrest Li (Tianjin-born Singaporean); large China-origin engineering population | G37: ● | H37: ● | I37: ● | J37: ● | K37: ● | L37: Mega-scale | M37: AI CoE (Jul 2026); MariBank (MAS-licensed digital bank) now in scope of MAS AI Risk Guidelines | N37: Add MariBank as an AI Risk/Gov entry point; Shopee Trust & Safety for AI Security | O37: High | P37: Confirmed | Q37: Wikipedia (Forrest Li); company sites | R37: v2 new | S37: v2: replaces v1 row — added MariBank (AI Risk) and founder link | T37: Not started
A38: 34 | B38: Bigo Technology (JOYY) | C38: BIGO 欢聚 | D38: Tech Giants (Regional / Global HQ) | E38: B | F38: Chinese-founded, Singapore-headquartered live-streaming company; 6 R&D centres worldwide | G38: ● | I38: ● | K38: ● | L38: Large | M38: Live-streaming content moderation, recsys and ads all data/AI heavy | N38: Pitch data engineers + Trust & Safety / AI content-security engineers; Mandarin-speaking management | O38: Medium-High | P38: Confirmed | Q38: Company job-board profile | R38: v2 new | T38: Not started
A39: 35 | B39: Trip.com Group Singapore | C39: 携程 | D39: Tech Giants (Regional / Global HQ) | E39: B | F39: Chinese-founded; principal executive offices moved to Singapore | G39: ● | I39: ○ | K39: ○ | L39: Large, HQ relocating | M39: Principal executive offices have moved to Singapore; core team continues to expand | N39: HQ relocation means decisions are now local — a priority account | O39: Medium | P39: Confirmed | Q39: Wikipedia / company announcements | R39: v1 | T39: Not started
A40: 36 | B40: Huawei Singapore (Huawei Cloud / Huawei Intl) | C40: 华为新加坡 | D40: Tech Giants (Regional / Global HQ) | E40: A | F40: Chinese HQ; regional cloud + R&D | G40: ● | H40: ○ | I40: ● | K40: ● | L40: Mega-scale | M40: Huawei said it will increase SG campus recruitment in 2026; Huawei Cloud SG region | N40: Lateral roles in cloud/AI/security; long decision chain, Mandarin advantage | O40: Medium | P40: Confirmed | Q40: HCAmag / People Matters 2026 | R40: v2 new | T40: Not started
A41: 37 | B41: Lark (Feishu) International | C41: 飞书 Lark | D41: Tech Giants (Regional / Global HQ) | E41: A | F41: ByteDance made Singapore Lark's global HQ | H41: ● | I41: ● | K41: ● | L41: Large | M41: Enterprise SaaS selling into regulated industries → security/compliance engineering | N41: Pitch enterprise security, AI governance (data residency), backend SWE | O41: Medium | P41: Likely | Q41: KrASIA (older); 2025 SG job postings | R41: v2 new | T41: Not started
A42: 38 | B42: BytePlus (ByteDance enterprise cloud) | C42: BytePlus | D42: Tech Giants (Regional / Global HQ) | E42: A | F42: ByteDance's B2B cloud/AI arm, SG-based | G42: ● | H42: ● | K42: ● | L42: Large | M42: Selling ByteDance models/recsys to SEA enterprises | N42: Separate account from TikTok; solutions/data engineers + AI governance for enterprise clients | O42: Medium | P42: Likely | Q42: Company website | R42: v2 new | T42: Not started
A43: 39 | B43: Tencent — Level Infinite (games publishing) | C43: 腾讯 Level Infinite | D43: Tech Giants (Regional / Global HQ) | E43: A | F43: Tencent Games' global publishing arm, HQ Amsterdam + Singapore | G43: ● | K43: ● | L43: Large | M43: Global game publishing → player data, live-ops analytics, anti-cheat | N43: Separate BD contact from Tencent corporate; pitch game data engineers | O43: Medium | P43: Likely | Q43: Company website | R43: v2 new | T43: Not started
A44: 40 | B44: Lazada (Alibaba) | C44: Lazada | D44: Tech Giants (Regional / Global HQ) | E44: A | F44: Alibaba-owned, SG HQ; many China-transferred tech leaders | G44: ● | J44: ○ | K44: ● | L44: Mega-scale | M44: Ongoing tech restructuring; data + AI search/ads teams | N44: Split from v1 Alibaba row — SG-based tech leadership makes local decisions | O44: Medium | P44: Confirmed | Q44: Company website | R44: v2 new | T44: Not started
A45: 41 | B45: Keeta (Meituan) — SEA | C45: 美团 Keeta | D45: Tech Giants (Regional / Global HQ) | E45: A | F45: Meituan's overseas food delivery | G45: ● | K45: ○ | L45: Emerging | M45: Explosive overseas expansion (v1) | N45: Confirm SG team size | O45: Medium | P45: To verify | Q45: Industry trend synthesis (v1) | R45: v2.1 | S45: v2.1: split from grouped row 'Meituan Keeta / Pinduoduo Temu (v1)' | T45: Not started
A46: 42 | B46: Temu (PDD) — SEA | C46: 拼多多 Temu | D46: Tech Giants (Regional / Global HQ) | E46: A | F46: PDD's cross-border e-commerce | G46: ● | K46: ○ | L46: Mega-scale | M46: SEA expansion (v1) | N46: Confirm SG team size | O46: Medium | P46: To verify | Q46: Industry trend synthesis (v1) | R46: v2.1 | S46: v2.1: split from grouped row 'Meituan Keeta / Pinduoduo Temu (v1)' | T46: Not started
A47: 43 | B47: Lenovo (APAC) | C47: 联想 | D47: Tech Giants (Regional / Global HQ) | E47: A | F47: Chinese HQ; APAC presence in Singapore (verify scope) | G47: ○ | K47: ● | L47: Mega-scale | M47: AI PC / infrastructure push | N47: Verify which functions sit in SG | O47: Low | P47: To verify | Q47: Company website | R47: v2 new | T47: Not started
A48: 44 | B48: OPPO | C48: OPPO | D48: Tech Giants (Regional / Global HQ) | E48: A | F48: APAC hub is in Kuala Lumpur; SG is commercial (flagship store) | K48: ○ | L48: Mega-scale | M48: No SG tech team evidence | N48: Low — SG is sales, not tech | O48: Low | P48: Likely | Q48: Marketing-Interactive | R48: v2.1 | S48: v2.1: split from grouped row 'Chinese handset makers' | T48: Not started
A49: 45 | B49: Transsion (TECNO) | C49: 传音控股 | D49: Tech Giants (Regional / Global HQ) | E49: A | F49: Launched TECNO foldables in SG | K49: ○ | L49: Mega-scale | M49: SG market entry; no SG tech team found | N49: Radar | O49: Radar | P49: To verify | Q49: SCMP | R49: v2.1 | S49: v2.1: split from grouped row 'Chinese handset makers' | T49: Not started
A50: 46 | B50: vivo | C50: vivo | D50: Tech Giants (Regional / Global HQ) | E50: A | F50: No SG regional HQ or R&D found | K50: ○ | L50: Mega-scale | M50: — | N50: Radar only | O50: Radar | P50: To verify | Q50: Search found none | R50: v2.1 | S50: v2.1: split from grouped row 'Chinese handset makers' | T50: Not started
A51: 47 | B51: realme | C51: realme | D51: Tech Giants (Regional / Global HQ) | E51: A | F51: No SG regional HQ or R&D found | K51: ○ | L51: Mega-scale | M51: — | N51: Radar only | O51: Radar | P51: To verify | Q51: Search found none | R51: v2.1 | S51: v2.1: split from grouped row 'Chinese handset makers' | T51: Not started
A52: 48 | B52: Honor | C52: 荣耀 | D52: Tech Giants (Regional / Global HQ) | E52: A | F52: No SG regional HQ or R&D found | K52: ○ | L52: Mega-scale | M52: — | N52: Radar only | O52: Radar | P52: To verify | Q52: Search found none | R52: v2.1 | S52: v2.1: split from grouped row 'Chinese handset makers' | T52: Not started
A53: 49 | B53: ADVANCE.AI / Atome (Advance Intelligence Group) | C53: ADVANCE.AI | D53: Fintech / Payments / Digital Banks | E53: B | F53: Chinese-founded, SG-headquartered AI risk / KYC / BNPL group | G53: ● | H53: ● | I53: ● | J53: ● | K53: ● | L53: Unicorn | M53: Core product = AI risk models, fraud & deepfake detection; licensed lending → MAS AI Risk Guidelines | N53: Perfect AI Risk + AI Security fit with Mandarin-speaking leadership — top new fintech target | O53: High | P53: Likely | Q53: Company website | R53: v2 new | T53: Not started
A54: 50 | B54: FinVolution Group | C54: 信也科技 | D54: Fintech / Payments / Digital Banks | E54: A | F54: Shanghai-based, NYSE-listed; overseas brands AdaKami (Indonesia), JuanHand (Philippines); also Pakistan, Australia | G54: ● | H54: ○ | J54: ● | K54: ● | L54: Large; overseas = 27.3% of revenue (Q2 2026) | M54: Overseas revenue +18% YoY to RMB930M in Q2 2026; separate overseas segment from Q1 2026; target >50% of revenue overseas by 2030 | N54: Biggest Chinese credit-tech going abroad — localising risk-control systems = AI Risk + data engineers. Ask where the regional hub / overseas tech team sits (SG entity to verify) | O54: Medium-High | P54: Likely | Q54: FinVolution Q1 & Q2 2026 earnings calls | R54: v2.1 | S54: v2.1: split from grouped row 'Chinese credit-tech going abroad' | T54: Not started
A55: 51 | B55: SUNRATE | C55: SUNRATE | D55: Fintech / Payments / Digital Banks | E55: C | F55: Global HQ in Singapore; offices in HK, Shanghai, Jakarta, London; acquiring China's Transfar Pay; co-founders Joshua Bao & Paul Meng (verify background) | G55: ● | H55: ● | J55: ● | K55: ● | L55: Scale-up; MAS MPI + CMS licences | M55: Expanding into treasury products (2025); DBS partnership; China payment licence via acquisition | N55: Licensed + China links → AI Risk/Gov + data; SG HQ makes decisions locally | O55: Medium-High | P55: Confirmed | Q55: sunrate.com newsroom; Vietnam News 2025 | R55: v2.1 | S55: v2.1: new — Chinese cross-border payments | T55: Not started
A56: 52 | B56: PingPong | C56: PingPong 乒乓智能 | D56: Fintech / Payments / Digital Banks | E56: A | F56: Chinese HQ / mainland parent | G56: ● | H56: ● | L56: Mid-to-large, licensed entity | M56: Chinese founding team, holds an MAS payments license; compliance and data needs are both significant | N56: Licensed entities have hard-constraint data governance/compliance talent needs — a strong potential AI Governance client | O56: Medium | P56: Likely | Q56: MAS licensee registry / company information synthesis | R56: v1 | S56: v2 CORRECTION: v1 labelled PingPong as 连连数字 — that is LianLian (separate row added) | T56: Not started
A57: 53 | B57: XTransfer | C57: XTransfer | D57: Fintech / Payments / Digital Banks | E57: A | F57: Chinese HQ / mainland parent | G57: ● | L57: Mid-size, Singapore team size to verify | M57: Chinese-background cross-border trade tech company with an active overseas push | N57: Verify actual Singapore team size before committing BD resources | O57: Medium | P57: Confirmed | Q57: Company information synthesis | R57: v1 | S57: v2.1: upgraded — received MAS Major Payment Institution licence (1 Jan 2025); add AI Risk/Gov | T57: Not started
A58: 54 | B58: Airwallex | C58: 空中云汇 | D58: Fintech / Payments / Digital Banks | E58: C | F58: Chinese-heritage founders (Melbourne) | G58: ● | H58: ● | L58: Large unicorn, Chinese-founding team | M58: Founded in Melbourne by a Chinese-heritage founding team; Singapore is one of its licensed operating bases, with both governance and data needs | N58: A licensed fintech company — good fit to pitch both directions at once | O58: Medium | P58: Likely | Q58: Company background synthesis | R58: v1 | T58: Not started
A59: 55 | B59: LianLian Global | C59: 连连国际 | D59: Fintech / Payments / Digital Banks | E59: A | F59: Chinese cross-border payments (LianLian DigiTech); SG entity | G59: ● | H59: ● | J59: ● | L59: Large, HK-listed parent | M59: Cross-border payments compliance; NB v1 mislabelled PingPong as 连连数字 — LianLian is a separate company | N59: Same compliance/data pitch as PingPong | O59: Medium | P59: Likely | Q59: Company website | R59: v2 new | T59: Not started
A60: 56 | B60: YouTrip | C60: YouTrip | D60: Fintech / Payments / Digital Banks | E60: C | F60: SG multi-currency wallet; HK-born co-founder (Caecilia Chu) | G60: ● | J60: ● | K60: ● | L60: Scale-up, MAS-licensed | M60: Licensed → fraud/AI risk + data needs | N60: Smaller TA team; pitch DE + fraud ML | O60: Medium | P60: Confirmed | Q60: Company website | R60: v2 new | T60: Not started
A61: 57 | B61: GXS Bank (Grab–Singtel) | C61: GXS | D61: Fintech / Payments / Digital Banks | E61: D | F61: Digital bank; engineering staff incl. many China-origin engineers (verify) | G61: ● | H61: ● | J61: ● | K61: ● | L61: Digital bank | M61: MAS AI Risk Guidelines 12-month transition | N61: AI Gov/Risk + DE bundle | O61: Medium | P61: Likely | Q61: MAS | R61: v2 new | S61: MindForge Phase 2 member (MAS) | T61: Not started
A62: 58 | B62: TrustDecision (Tongdun International) | C62: 同盾科技 | D62: Fintech / Payments / Digital Banks | E62: A | F62: Hangzhou AI risk-control firm; overseas brand TrustDecision launched in Singapore (2022); Temasek co-led 2017 round | G62: ● | I62: ● | J62: ● | L62: Large | M62: Overseas brand for fraud / credit / compliance risk; first foreign firm with Indonesia OJK credit-scoring status | N62: Pure AI Risk vendor — risk-model and anti-fraud engineers; confirm SG headcount | O62: Medium | P62: Likely | Q62: TechNode Global / PRNewswire Jul 2022; BIIA | R62: v2.1 | S62: v2.1: split from grouped row 'Chinese credit-tech going abroad' | T62: Not started
A63: 59 | B63: OneConnect (Ping An) | C63: 金融壹账通 | D63: Fintech / Payments / Digital Banks | E63: A | F63: Ping An's fintech SaaS; subsidiaries in Singapore, Indonesia, HK | G63: ● | H63: ● | J63: ● | K63: ● | L63: Large | M63: Sep 2026: chairman says Chinese fintech going abroad has 'entered a new stage' — SEA banks want AI risk-control infrastructure | N63: Vendor selling AI risk to SEA banks → AI Risk + delivery engineers; Mandarin-speaking leadership | O63: Medium | P63: Likely | Q63: Tencent News 15 Sep 2026; Jiemian | R63: v2.1 | S63: v2.1: split from grouped row 'Chinese credit-tech going abroad' | T63: Not started
A64: 60 | B64: 2C2P (Antom / Ant International) | C64: 2C2P | D64: Fintech / Payments / Digital Banks | E64: A | F64: Ant International-owned payments platform | G64: ● | I64: ● | J64: ● | L64: Large | M64: Received MAS MPI licence 2025 | N64: Approach together with Ant International contacts | O64: Medium | P64: Confirmed | Q64: Fintech News SG 2025 | R64: v2.1 | S64: v2.1: new — Chinese cross-border payments | T64: Not started
A65: 61 | B65: Green Link Digital Bank | C65: 绿地数字银行 | D65: Fintech / Payments / Digital Banks | E65: A | F65: Digital wholesale bank led by Shanghai's Greenland Financial; MAS-licensed | G65: ● | H65: ● | J65: ● | L65: Small bank | M65: MAS AI Risk Guidelines apply to all licensed banks incl. DWBs | N65: Small but Mandarin-speaking leadership; AI Gov/Risk first hire | O65: Low-Medium | P65: Likely | Q65: MAS DWB licence announcement (2020) | R65: v2 new | T65: Not started
A66: 62 | B66: Trust Bank (StanChart–FairPrice) | C66: Trust Bank | D66: Fintech / Payments / Digital Banks | E66: E | F66: Digital bank | G66: ● | H66: ● | J66: ● | L66: Digital bank | M66: MAS AI Risk Guidelines 12-month transition | N66: AI Gov/Risk + DE bundle | O66: Low-Medium | P66: Likely | Q66: MAS | R66: v2 new | T66: Not started
A67: 63 | B67: LexinFintech | C67: 乐信 | D67: Fintech / Payments / Digital Banks | E67: A | F67: Shenzhen-based, Nasdaq-listed; started SEA + South America business (limited disclosure) | G67: ● | J67: ● | K67: ● | L67: Large | M67: Sep 2025: Asian Banker led 30 overseas bankers to see Lexin's AI-agent work; overseas customer-acquisition cost cut ~20% | N67: AI-agent + risk capabilities marketed overseas — ask about SEA team location | O67: Low-Medium | P67: To verify | Q67: GlobeNewswire Sep 2025; Jiemian 2025 | R67: v2.1 | S67: v2.1: split from grouped row 'Chinese credit-tech going abroad' | T67: Not started
A68: 64 | B68: Jiayin Group | C68: 嘉银科技 | D68: Fintech / Payments / Digital Banks | E68: A | F68: Shanghai-based, Nasdaq-listed; Indonesia lending business | G68: ● | J68: ● | L68: Mid-size | M68: Tripled Indonesia loan volume (2025); pledged further overseas expansion | N68: Verify whether SEA risk/data team is hired out of SG | O68: Low-Medium | P68: To verify | Q68: Jiemian 2025 | R68: v2.1 | S68: v2.1: split from grouped row 'Chinese credit-tech going abroad' | T68: Not started
A69: 65 | B69: UnionPay International (Singapore) | C69: 银联国际 | D69: Fintech / Payments / Digital Banks | E69: A | F69: Chinese card network's international arm with SEA presence | G69: ● | I69: ● | J69: ● | L69: Large | M69: Cross-border payments fraud/risk | N69: Verify SG tech headcount | O69: Low-Medium | P69: To verify | Q69: Public information | R69: v2.1 | S69: v2.1: new — Chinese cross-border payments | T69: Not started
A70: 66 | B70: Qifu Technology (ex-360 DigiTech) | C70: 奇富科技 | D70: Fintech / Payments / Digital Banks | E70: A | F70: Shanghai-based, Nasdaq/HK-listed credit-tech | G70: ● | J70: ● | L70: Large | M70: No clear overseas footprint found in public sources | N70: Radar — watch for overseas launch | O70: Radar | P70: To verify | Q70: Public filings | R70: v2.1 | S70: v2.1: split from grouped row 'Chinese credit-tech going abroad' | T70: Not started
A71: 67 | B71: Yiren Digital | C71: 宜人智科 | D71: Fintech / Payments / Digital Banks | E71: A | F71: Beijing-based, NYSE-listed; exploring North America & Middle East | G71: ● | J71: ● | L71: Mid-size | M71: Expects >10% revenue abroad by 2026 — not SEA-focused | N71: Radar | O71: Radar | P71: To verify | Q71: Jiemian 2025 | R71: v2.1 | S71: v2.1: split from grouped row 'Chinese credit-tech going abroad' | T71: Not started
A72: 68 | B72: Pintec | C72: 品钛 | D72: Fintech / Payments / Digital Banks | E72: A | F72: Beijing fintech-tech provider; historic SEA JV activity | G72: ● | J72: ● | L72: Small | M72: No current overseas info found | N72: Radar | O72: Radar | P72: To verify | Q72: — | R72: v2.1 | S72: v2.1: split from grouped row 'Chinese credit-tech going abroad' | T72: Not started
A73: 69 | B73: Akulaku | C73: Akulaku | D73: Fintech / Payments / Digital Banks | E73: C | F73: Chinese-founded (William Li), Indonesia-based, Ant-backed digital finance | G73: ● | J73: ● | L73: Unicorn | M73: SEA lending + digital bank stake | N73: Verify any SG-based tech/risk hiring | O73: Radar | P73: To verify | Q73: Public information | R73: v2.1 | S73: v2.1: split from grouped row 'Chinese credit-tech going abroad' | T73: Not started
A74: 70 | B74: Moomoo (Futu) Singapore | C74: 富途 moomoo | D74: Online Brokerages / Wealth Platforms | E74: A | F74: Shenzhen-founded Futu; Moomoo SG is MAS-licensed with very large SG user base | G74: ● | H74: ● | I74: ● | J74: ● | K74: ● | L74: Large, Nasdaq-listed parent | M74: MAS-regulated → AI Risk Guidelines; heavy data/AI (AI investing assistant) | N74: Top new target: Mandarin-speaking management + regulatory deadline + data volume | O74: High | P74: Confirmed | Q74: MAS FI directory; company website | R74: v2 new | T74: Not started
A75: 71 | B75: Tiger Brokers (UP Fintech) Singapore | C75: 老虎证券 | D75: Online Brokerages / Wealth Platforms | E75: A | F75: Chinese-founded; SG is its key international hub | G75: ● | H75: ● | I75: ● | J75: ● | K75: ● | L75: Large, Nasdaq-listed parent | M75: MAS-licensed; AI features + compliance | N75: Same pitch as Moomoo — run both in parallel | O75: High | P75: Confirmed | Q75: MAS FI directory; company website | R75: v2 new | T75: Not started
A76: 72 | B76: Webull Singapore | C76: Webull | D76: Online Brokerages / Wealth Platforms | E76: C | F76: Founded by ex-Alibaba exec (Wang Anquan); SG licensed entity | G76: ● | H76: ● | J76: ● | L76: Large | M76: MAS-licensed | N76: AI Risk/Gov + data | O76: Medium | P76: Likely | Q76: Company website | R76: v2 new | T76: Not started
A77: 73 | B77: Longbridge Singapore | C77: 长桥证券 | D77: Online Brokerages / Wealth Platforms | E77: A | F77: Chinese online broker expanding SG | G77: ● | H77: ● | J77: ● | K77: ● | L77: Mid-size | M77: Expansion phase | N77: Verify MAS licence status/team size | O77: Medium | P77: To verify | Q77: Company website | R77: v2 new | T77: Not started
A78: 74 | B78: Bullet | D78: Crypto / Web3 | E78: E | F78: Crypto HFT | G78: ● | I78: ○ | K78: ○ | M78: Founded by the former Zeta Markets team, backed by top crypto funds including Electric Capital, Jump Capital, Race Capital, and Wintermute | N78: A newly funded early-stage team, expanding without a mature HR setup yet — high value for agency involvement | O78: High | P78: Likely | Q78: Industry reporting synthesis | R78: v1 | T78: Not started
A79: 75 | B79: OKX Singapore | C79: 欧易 | D79: Crypto / Web3 | E79: A | F79: Chinese HQ / mainland parent | G79: ● | I79: ○ | K79: ○ | L79: Large, Chinese background | M79: Singapore hiring for roles such as Data Operations Engineer, requiring SQL/Python | N79: Chinese-background exchange — strong language/culture fit | O79: Medium-High | P79: Confirmed | Q79: Public careers page | R79: v1 | S79: v2: add AI Risk/Gov if SG entity is MAS-licensed (verify) | T79: Not started
A80: 76 | B80: Bitdeer | C80: 比特小鹿 | D80: Crypto / Web3 | E80: B | F80: Founded by Jihan Wu (Bitmain co-founder); Singapore HQ, Nasdaq-listed | G80: ● | I80: ● | K80: ● | L80: Large | M80: Pivoting into AI cloud / HPC on top of mining | N80: AI infra + data engineers; Mandarin-speaking leadership | O80: Medium-High | P80: Confirmed | Q80: Company filings | R80: v2 new | T80: Not started
A81: 77 | B81: Binance Singapore | C81: 币安 | D81: Crypto / Web3 | E81: C | F81: Founder CZ of Chinese descent | G81: ● | I81: ○ | K81: ○ | L81: Mega-scale, one of the world's largest exchanges | M81: Founded by Changpeng Zhao, who is of Chinese descent; large-scale ongoing hiring in Singapore (287 open roles) | N81: World's largest exchange with huge headcount volume — the top priority target in this category | O81: Medium | P81: To verify | Q81: Indeed / Glassdoor job listing statistics | R81: v1 | S81: v2 CAUTION: Binance.sg exited Singapore in 2021 and holds no MAS licence — verify the 287 roles are truly SG-based | T81: Not started
A82: 78 | B82: Matrixport Singapore | C82: Matrixport | D82: Crypto / Web3 | E82: B | F82: Founded by Jihan Wu (ex-Bitmain); SG core base | G82: ● | I82: ○ | K82: ○ | L82: Mid-size, founded by former Bitmain executives | M82: Founding team has a strong Chinese background; Singapore is its core operating base | N82: Strong founding-team fit — prioritize outreach | O82: Medium | P82: Likely | Q82: Company background synthesis | R82: v1 | T82: Not started
A83: 79 | B83: Amber Group Singapore | C83: Amber Group | D83: Crypto / Web3 | E83: B | F83: Chinese-founded crypto fintech; HK/SG | G83: ● | I83: ○ | K83: ○ | L83: Mid-size, HK/Singapore dual base | M83: Chinese-background crypto fintech company continuing to build out its Singapore team | N83: Verify current specific role needs | O83: Medium | P83: Likely | Q83: Company background synthesis | R83: v1 | T83: Not started
A84: 80 | B84: Coinhako | C84: Coinhako | D84: Crypto / Web3 | E84: C | F84: Singaporean-Chinese co-founders | G84: ● | I84: ○ | K84: ○ | M84: Locally licensed exchange, continuing to build data infrastructure | N84: Licensed entity may also need AI/data-governance talent — pitch both directions as a bundle | O84: Medium | P84: Confirmed | Q84: Glassdoor careers page | R84: v1 | T84: Not started
A85: 81 | B85: Paradex | D85: Crypto / Web3 | E85: E | F85: Crypto derivatives | G85: ● | I85: ○ | K85: ○ | M85: Multiple active data engineering and quant development roles open in Singapore | N85: An emerging crypto derivatives platform in expansion mode, short decision chain, fast BD conversion | O85: Medium | P85: Confirmed | Q85: Public careers page | R85: v1 | T85: Not started
A86: 82 | B86: Cobo | C86: Cobo | D86: Crypto / Web3 | E86: B | F86: Chinese-founded digital-asset custody (founders from F2Pool); SG-based | G86: ● | I86: ● | K86: ● | L86: Mid-size | M86: Custody = security-critical | N86: Security engineers + data | O86: Medium | P86: Likely | Q86: Company website | R86: v2 new | T86: Not started
A87: 83 | B87: Antalpha | C87: Antalpha | D87: Crypto / Web3 | E87: B | F87: Bitmain-linked crypto lending, SG HQ, Nasdaq IPO 2025 | G87: ● | J87: ● | K87: ● | L87: Mid-size | M87: Newly listed → compliance + risk build-out | N87: AI/credit risk + data | O87: Medium | P87: Likely | Q87: IPO filings 2025 | R87: v2 new | T87: Not started
A88: 84 | B88: Bitget | C88: Bitget | D88: Crypto / Web3 | E88: C | F88: CEO Gracy Chen (Singaporean-Chinese); large Asian team; does not serve SG retail | G88: ● | I88: ● | K88: ● | L88: Large | M88: Large hiring volume; verify SG-based roles | N88: Verify SG headcount before BD | O88: Low-Medium | P88: To verify | Q88: Public information | R88: v2 new | T88: Not started
A89: 85 | B89: Crypto.com | D89: Crypto / Web3 | E89: E | F89: SG-HQ'd exchange (non-Chinese founders) | G89: ● | I89: ● | J89: ● | K89: ● | L89: Large | M89: Large compliance + data teams | N89: AI Risk / compliance analytics | O89: Low-Medium | P89: Likely | Q89: Company careers page | R89: v2 new | T89: Not started
A90: 86 | B90: imToken | C90: imToken | D90: Crypto / Web3 | E90: B | F90: Chinese-founded Ethereum wallet; global HQ in Singapore | I90: ● | K90: ● | L90: Small-to-mid | M90: SG global HQ | N90: Wallet security + SWE | O90: Low-Medium | P90: Confirmed | Q90: Investing.com / Forkast | R90: v2.1 | S90: v2.1: split from grouped row 'imToken / TokenPocket / Particle Network' | T90: Not started
A91: 87 | B91: TokenPocket | C91: TokenPocket | D91: Crypto / Web3 | E91: B | F91: Chinese-founded multi-chain wallet; SG entity to verify | I91: ● | K91: ● | L91: Small-to-mid | M91: — | N91: Verify activity | O91: Low | P91: To verify | Q91: Public information | R91: v2.1 | S91: v2.1: split from grouped row 'imToken / TokenPocket / Particle Network' | T91: Not started
A92: 88 | B92: Particle Network | C92: Particle Network | D92: Crypto / Web3 | E92: B | F92: Chinese-founded Web3 infra; SG entity to verify | I92: ● | K92: ● | L92: Small-to-mid | M92: — | N92: Verify activity | O92: Low | P92: To verify | Q92: Public information | R92: v2.1 | S92: v2.1: split from grouped row 'imToken / TokenPocket / Particle Network' | T92: Not started
A93: 89 | B93: WeRide | C93: 文远知行 | D93: Robotics / Autonomous Driving | E93: A | F93: Chinese AV company; runs Ai.R robotaxi service with Grab in Punggol | G93: ● | J93: ● | K93: ● | L93: Nasdaq-listed | M93: Live SG deployment with Grab; safety validation + ops data | N93: AV safety/validation = AI Risk; also simulation & data pipeline engineers | O93: Medium | P93: Confirmed | Q93: Bloomberg 20 Sep 2025 | R93: v2 new | T93: Not started
A94: 90 | B94: Pony.ai | C94: 小马智行 | D94: Robotics / Autonomous Driving | E94: A | F94: Chinese AV company; SG service with ComfortDelGro | G94: ● | J94: ● | K94: ● | L94: Nasdaq/HK-listed | M94: Apr 2026: approval for by-invite rides in SG, final phase before public service | N94: Public launch → local engineering/ops build-out; pitch AV safety + data engineers | O94: Medium | P94: Confirmed | Q94: Pony.ai press release Apr 2026 | R94: v2 new | T94: Not started
A95: 91 | B95: AgiBot | C95: 智元机器人 | D95: Robotics / Autonomous Driving | E95: A | F95: Chinese humanoid-robot leader; entered SG Oct 2025 and expanding | K95: ● | L95: Unicorn | M95: Steady SG expansion since market entry | N95: Early relationship — robotics SWE + solutions engineers | O95: Medium | P95: Likely | Q95: Industry reporting 2026 | R95: v2 new | T95: Not started
A96: 92 | B96: Unitree Robotics | C96: 宇树科技 | D96: Robotics / Autonomous Driving | E96: A | F96: In 2026 Punggol large-scale robotics trial; investor pitched SG as route to US buyers | K96: ● | L96: Unicorn | M96: SG trial participation; Shanghai humanoid incubator plans SG branch (Oct 2026) | N96: Radar → medium if SG entity is set up | O96: Low-Medium | P96: To verify | Q96: CNBC Aug 2026 (via aggregator); asianews.network | R96: v2 new | T96: Not started
A97: 93 | B97: Geek+ | C97: 极智嘉 | D97: Robotics / Autonomous Driving | E97: A | F97: Warehouse-robotics leader; offices incl. Singapore | G97: ● | K97: ● | L97: Large (HK-listed) | M97: SG office | N97: Robotics SWE / solutions | O97: Low-Medium | P97: Likely | Q97: DC Velocity | R97: v2.1 | S97: v2.1: split from grouped row 'Pudu / Keenon / Gaussian' | T97: Not started
A98: 94 | B98: Keenon Robotics | C98: 擎朗智能 | D98: Robotics / Autonomous Driving | E98: A | F98: Service-robot maker; used Singapore as launchpad with SoftBank Robotics (2021) | K98: ● | L98: Unicorn (SoftBank VF2-backed) | M98: SG launchpad | N98: Verify SG engineering vs. sales | O98: Low | P98: Likely | Q98: SoftBank Robotics APAC 2021 | R98: v2.1 | S98: v2.1: split from grouped row 'Pudu / Keenon / Gaussian' | T98: Not started
A99: 95 | B99: Pudu Robotics | C99: 普渡科技 | D99: Robotics / Autonomous Driving | E99: A | F99: Service-robot maker widely deployed in SG F&B | K99: ● | L99: Unicorn | M99: No SG entity confirmed | N99: Verify | O99: Low | P99: To verify | Q99: Public information | R99: v2.1 | S99: v2.1: split from grouped row 'Pudu / Keenon / Gaussian' | T99: Not started
A100: 96 | B100: Gaussian Robotics | C100: 高仙机器人 | D100: Robotics / Autonomous Driving | E100: A | F100: Cleaning-robot maker with SEA deployments | K100: ● | L100: Late-stage | M100: No SG entity confirmed | N100: Verify | O100: Low | P100: To verify | Q100: Public information | R100: v2.1 | S100: v2.1: split from grouped row 'Pudu / Keenon / Gaussian' | T100: Not started
A101: 97 | B101: Siasun Robot & Automation | C101: 新松机器人 | D101: Robotics / Autonomous Driving | E101: A | F101: Set up an automation company in Singapore (2017) | K101: ● | L101: Large | M101: SG subsidiary | N101: Low volume | O101: Low | P101: Likely | Q101: China Daily 2018 | R101: v2.1 | S101: v2.1: split from grouped row 'Pudu / Keenon / Gaussian' | T101: Not started
...

Sheet LinkedIn Search Plan
A1: LinkedIn Recruiter — Search Plan (one row per company; paste the strings into Recruiter's filters)
A2: How to use: in Recruiter, open the project → Search → Current company = column C, Location = Singapore, Job titles (Boolean) = column F for hiring managers, then column G for TA/HR. Save the 2-4 best people per company into the project. Column I opens a regular LinkedIn people search (pre-filtered to Singapore) for a quick check. Yellow columns are yours.
A4: # | B4: Company | C4: LinkedIn company filter (check exact page) | D4: Priority | E4: Project / Tag | F4: Hiring-manager titles (Boolean) | G4: TA / HR titles (Boolean) | H4: Founder string (startups) | I4: Quick LinkedIn search | J4: Template (1st msg) | K4: Language | L4: # people saved | M4: Names saved / notes | N4: Status
A5: 1 | B5: Plaud | C5: Plaud | D5: High | E5: BD-W1 High | F5: ("head of data" OR "data engineering manager" OR "director of data" OR "data platform" OR "head of data engineering" OR "chief data officer" OR CTO OR "VP engineering" OR "head of engineering" OR "engineering director" OR "engineering manager") | G5: ("talent acquisition" OR recruiter OR "recruitment" OR HRBP OR "head of HR" OR "people partner" OR "human resources") | H5: (founder OR "co-founder" OR CEO) | I5: Open search | J5: T2-CN | K5: CN (EN if local hire) | N5: Not started
A6: 2 | B6: MiroMind (Shanda Group) | C6: MiroMind | D6: High | E6: BD-W1 High | F6: (CISO OR "head of security" OR "security engineering" OR "AI security" OR "trust and safety" OR "head of cybersecurity" OR CTO OR "VP engineering" OR "head of engineering" OR "engineering director" OR "engineering manager") | G6: ("talent acquisition" OR recruiter OR "recruitment" OR HRBP OR "head of HR" OR "people partner" OR "human resources") | H6: (founder OR "co-founder" OR CEO) | I6: Open search | J6: T2-CN | K6: CN (EN if local hire) | N6: Not started
A7: 3 | B7: Ropedia | C7: Ropedia | D7: High | E7: BD-W1 High | F7: ("head of data" OR "data engineering manager" OR "director of data" OR "data platform" OR "head of data engineering" OR "chief data officer" OR CTO OR "VP engineering" OR "head of engineering" OR "engineering director" OR "engineering manager") | G7: ("talent acquisition" OR recruiter OR "recruitment" OR HRBP OR "head of HR" OR "people partner" OR "human resources") | H7: (founder OR "co-founder" OR CEO) | I7: Open search | J7: T2-EN | K7: EN (CN if Mandarin) | N7: Not started
A8: 4 | B8: OneByZero (OBZ) | C8: OneByZero | D8: High | E8: BD-W1 High | F8: ("head of data" OR "data engineering manager" OR "director of data" OR "data platform" OR "head of data engineering" OR "chief data officer" OR "AI governance" OR "responsible AI" OR "data governance" OR "head of compliance" OR "AI ethics" OR CTO) | G8: ("talent acquisition" OR recruiter OR "recruitment" OR HRBP OR "head of HR" OR "people partner" OR "human resources") | H8: (founder OR "co-founder" OR CEO) | I8: Open search | J8: T2-EN | K8: EN | N8: Not started
A9: 5 | B9: MiniMax | C9: MiniMax | D9: High | E9: BD-W1 High | F9: ("head of data" OR "data engineering manager" OR "director of data" OR "data platform" OR "head of data engineering" OR "chief data officer" OR "AI governance" OR "responsible AI" OR "data governance" OR "head of compliance" OR "AI ethics" OR CTO) | G9: ("talent acquisition" OR recruiter OR "recruitment" OR HRBP OR "head of HR" OR "people partner" OR "human resources") | I9: Open search | J9: T2-CN | K9: CN (EN if local hire) | N9: Not started
A10: 6 | B10: ByteDance Seed (AI research) — Singapore lab | C10: ByteDance Seed | D10: High | E10: BD-W1 High | F10: ("head of data" OR "data engineering manager" OR "director of data" OR "data platform" OR "head of data engineering" OR "chief data officer" OR CISO OR "head of security" OR "security engineering" OR "AI security" OR "trust and safety" OR "head of cybersecurity") | G10: ("talent acquisition" OR recruiter OR "recruitment" OR HRBP OR "head of HR" OR "people partner" OR "human resources") | I10: Open search | J10: T2-CN | K10: CN (EN if local hire) | N10: Not started
A11: 7 | B11: ByteDance / TikTok Singapore | C11: ByteDance OR TikTok | D11: High | E11: BD-W1 High | F11: ("head of data" OR "data engineering manager" OR "director of data" OR "data platform" OR "head of data engineering" OR "chief data officer" OR "AI governance" OR "responsible AI" OR "data governance" OR "head of compliance" OR "AI ethics") | G11: ("talent acquisition" OR recruiter OR "recruitment" OR HRBP OR "head of HR" OR "people partner" OR "human resources") | I11: Open search | J11: T1-CN | K11: CN (EN if local hire) | N11: Not started
A12: 8 | B12: Alibaba Group / Alibaba Cloud International (Singapore) | C12: Alibaba Group OR Alibaba Cloud International | D12: High | E12: BD-W1 High | F12: ("head of data" OR "data engineering manager" OR "director of data" OR "data platform" OR "head of data engineering" OR "chief data officer" OR "AI governance" OR "responsible AI" OR "data governance" OR "head of compliance" OR "AI ethics") | G12: ("talent acquisition" OR recruiter OR "recruitment" OR HRBP OR "head of HR" OR "people partner" OR "human resources") | I12: Open search | J12: T1-CN | K12: CN (EN if local hire) | N12: Not started
A13: 9 | B13: Tencent Singapore | C13: Tencent | D13: High | E13: BD-W1 High | F13: ("head of data" OR "data engineering manager" OR "director of data" OR "data platform" OR "head of data engineering" OR "chief data officer") | G13: ("talent acquisition" OR recruiter OR "recruitment" OR HRBP OR "head of HR" OR "people partner" OR "human resources") | I13: Open search | J13: T1-CN | K13: CN (EN if local hire) | N13: Not started
A14: 10 | B14: Xiaomi Singapore | C14: Xiaomi | D14: High | E14: BD-W1 High | F14: ("head of data" OR "data engineering manager" OR "director of data" OR "data platform" OR "head of data engineering" OR "chief data officer") | G14: ("talent acquisition" OR recruiter OR "recruitment" OR HRBP OR "head of HR" OR "people partner" OR "human resources") | I14: Open search | J14: T1-CN | K14: CN (EN if local hire) | N14: Not started
A15: 11 | B15: SHEIN Singapore | C15: SHEIN | D15: High | E15: BD-W1 High | F15: ("head of data" OR "data engineering manager" OR "director of data" OR "data platform" OR "head of data engineering" OR "chief data officer") | G15: ("talent acquisition" OR recruiter OR "recruitment" OR HRBP OR "head of HR" OR "people partner" OR "human resources") | I15: Open search | J15: T1-CN | K15: CN (EN if local hire) | N15: Not started
A16: 12 | B16: Grab | C16: Grab | D16: High | E16: BD-W1 High | F16: ("head of data" OR "data engineering manager" OR "director of data" OR "data platform" OR "head of data engineering" OR "chief data officer") | G16: ("talent acquisition" OR recruiter OR "recruitment" OR HRBP OR "head of HR" OR "people partner" OR "human resources") | I16: Open search | J16: T1-EN | K16: EN | N16: Not started
A17: 13 | B17: Ant International (Alipay+, Antom, WorldFirst, ANEXT Bank) | C17: Ant International | D17: High | E17: BD-W1 High | F17: ("head of data" OR "data engineering manager" OR "director of data" OR "data platform" OR "head of data engineering" OR "chief data officer" OR "AI governance" OR "responsible AI" OR "data governance" OR "head of compliance" OR "AI ethics" OR CISO) | G17: ("talent acquisition" OR recruiter OR "recruitment" OR HRBP OR "head of HR" OR "people partner" OR "human resources") | I17: Open search | J17: T1-CN | K17: CN (EN if local hire) | N17: Not started
A18: 14 | B18: Sea / Shopee / Garena / MariBank | C18: Sea OR Shopee OR Garena OR MariBank | D18: High | E18: BD-W1 High | F18: ("head of data" OR "data engineering manager" OR "director of data" OR "data platform" OR "head of data engineering" OR "chief data officer" OR "AI governance" OR "responsible AI" OR "data governance" OR "head of compliance" OR "AI ethics" OR CISO) | G18: ("talent acquisition" OR recruiter OR "recruitment" OR HRBP OR "head of HR" OR "people partner" OR "human resources") | I18: Open search | J18: T1-EN | K18: EN (CN if Mandarin) | N18: Not started
A19: 15 | B19: ADVANCE.AI / Atome (Advance Intelligence Group) | C19: ADVANCE.AI OR Atome | D19: High | E19: BD-W1 High | F19: ("head of data" OR "data engineering manager" OR "director of data" OR "data platform" OR "head of data engineering" OR "chief data officer" OR "AI governance" OR "responsible AI" OR "data governance" OR "head of compliance" OR "AI ethics" OR CISO) | G19: ("talent acquisition" OR recruiter OR "recruitment" OR HRBP OR "head of HR" OR "people partner" OR "human resources") | I19: Open search | J19: T3-CN | K19: CN (EN if local hire) | N19: Not started
A20: 16 | B20: Moomoo (Futu) Singapore | C20: Moomoo | D20: High | E20: BD-W1 High | F20: ("head of data" OR "data engineering manager" OR "director of data" OR "data platform" OR "head of data engineering" OR "chief data officer" OR "AI governance" OR "responsible AI" OR "data governance" OR "head of compliance" OR "AI ethics" OR CISO) | G20: ("talent acquisition" OR recruiter OR "recruitment" OR HRBP OR "head of HR" OR "people partner" OR "human resources") | I20: Open search | J20: T3-CN | K20: CN (EN if local hire) | N20: Not started
A21: 17 | B21: Tiger Brokers (UP Fintech) Singapore | C21: Tiger Brokers | D21: High | E21: BD-W1 High | F21: ("head of data" OR "data engineering manager" OR "director of data" OR "data platform" OR "head of data engineering" OR "chief data officer" OR "AI governance" OR "responsible AI" OR "data governance" OR "head of compliance" OR "AI ethics" OR CISO) | G21: ("talent acquisition" OR recruiter OR "recruitment" OR HRBP OR "head of HR" OR "people partner" OR "human resources") | I21: Open search | J21: T3-CN | K21: CN (EN if local hire) | N21: Not started
A22: 18 | B22: Bullet | C22: Bullet | D22: High | E22: BD-W1 High | F22: ("head of data" OR "data engineering manager" OR "director of data" OR "data platform" OR "head of data engineering" OR "chief data officer") | G22: ("talent acquisition" OR recruiter OR "recruitment" OR HRBP OR "head of HR" OR "people partner" OR "human resources") | H22: (founder OR "co-founder" OR CEO) | I22: Open search | J22: T1-EN | K22: EN | N22: Not started
A23: 19 | B23: HoYoverse (miHoYo) Singapore | C23: HoYoverse | D23: High | E23: BD-W1 High | F23: ("head of data" OR "data engineering manager" OR "director of data" OR "data platform" OR "head of data engineering" OR "chief data officer") | G23: ("talent acquisition" OR recruiter OR "recruitment" OR HRBP OR "head of HR" OR "people partner" OR "human resources") | I23: Open search | J23: T1-CN | K23: CN (EN if local hire) | N23: Not started
A24: 20 | B24: Huatai Securities (Singapore) | C24: Huatai Securities | D24: High | E24: BD-W1 High | F24: ("head of data" OR "data engineering manager" OR "director of data" OR "data platform" OR "head of data engineering" OR "chief data officer" OR "AI governance" OR "responsible AI" OR "data governance" OR "head of compliance" OR "AI ethics" OR "model risk") | G24: ("talent acquisition" OR recruiter OR "recruitment" OR HRBP OR "head of HR" OR "people partner" OR "human resources") | I24: Open search | J24: T3-CN | K24: CN (EN if local hire) | N24: Not started
A25: 21 | B25: High-Flyer Quant (幻方量化, DeepSeek's parent) [verify SG team first] | C25: High-Flyer Quant | D25: High | E25: BD-W1 High | F25: ("head of data" OR "data engineering manager" OR "director of data" OR "data platform" OR "head of data engineering" OR "chief data officer") | G25: ("talent acquisition" OR recruiter OR "recruitment" OR HRBP OR "head of HR" OR "people partner" OR "human resources") | I25: Open search | J25: T5-CN | K25: CN (EN if local hire) | N25: Not started
A26: 22 | B26: MS Capital (Meridian & Saturn Capital) | C26: MS Capital | D26: High | E26: BD-W1 High | F26: ("head of data" OR "data engineering manager" OR "director of data" OR "data platform" OR "head of data engineering" OR "chief data officer") | G26: ("talent acquisition" OR recruiter OR "recruitment" OR HRBP OR "head of HR" OR "people partner" OR "human resources") | I26: Open search | J26: T5-CN | K26: CN (EN if local hire) | N26: Not started
A27: 23 | B27: Qube Research & Technologies | C27: Qube Research & Technologies | D27: High | E27: BD-W1 High | F27: ("head of data" OR "data engineering manager" OR "director of data" OR "data platform" OR "head of data engineering" OR "chief data officer") | G27: ("talent acquisition" OR recruiter OR "recruitment" OR HRBP OR "head of HR" OR "people partner" OR "human resources") | I27: Open search | J27: T5-EN | K27: EN | N27: Not started
A28: 24 | B28: Lingjun Investment | C28: Lingjun Investment | D28: High | E28: BD-W1 High | F28: ("head of data" OR "data engineering manager" OR "director of data" OR "data platform" OR "head of data engineering" OR "chief data officer" OR "model risk" OR "head of risk" OR "chief risk officer" OR "risk analytics" OR "fraud" OR "model validation") | G28: ("talent acquisition" OR recruiter OR "recruitment" OR HRBP OR "head of HR" OR "people partner" OR "human resources") | I28: Open search | J28: T5-CN | K28: CN (EN if local hire) | N28: Not started
A29: 25 | B29: EY Singapore | C29: EY | D29: High | E29: BD-W1 High | F29: ("AI governance" OR "responsible AI" OR "data governance" OR "chief data officer" OR "head of compliance" OR "AI ethics" OR "model risk" OR "head of risk" OR "chief risk officer" OR "risk analytics" OR "fraud" OR "model validation") | G29: ("talent acquisition" OR recruiter OR "recruitment" OR HRBP OR "head of HR" OR "people partner" OR "human resources") | I29: Open search | J29: T1-EN | K29: EN | N29: Not started
A30: 26 | B30: PwC Singapore | C30: PwC | D30: High | E30: BD-W1 High | F30: ("AI governance" OR "responsible AI" OR "data governance" OR "chief data officer" OR "head of compliance" OR "AI ethics") | G30: ("talent acquisition" OR recruiter OR "recruitment" OR HRBP OR "head of HR" OR "people partner" OR "human resources") | I30: Open search | J30: T1-EN | K30: EN | N30: Not started
A31: 27 | B31: DBS Bank | C31: DBS Bank | D31: High | E31: BD-W1 High | F31: ("AI governance" OR "responsible AI" OR "data governance" OR "chief data officer" OR "head of compliance" OR "AI ethics" OR "model risk" OR "head of risk" OR "chief risk officer" OR "risk analytics" OR "fraud" OR "model validation") | G31: ("talent acquisition" OR recruiter OR "recruitment" OR HRBP OR "head of HR" OR "people partner" OR "human resources") | I31: Open search | J31: T3-EN | K31: EN | N31: Not started
A32: 28 | B32: UOB | C32: UOB | D32: High | E32: BD-W1 High | F32: ("AI governance" OR "responsible AI" OR "data governance" OR "chief data officer" OR "head of compliance" OR "AI ethics" OR "model risk" OR "head of risk" OR "chief risk officer" OR "risk analytics" OR "fraud" OR "model validation") | G32: ("talent acquisition" OR recruiter OR "recruitment" OR HRBP OR "head of HR" OR "people partner" OR "human resources") | I32: Open search | J32: T3-EN | K32: EN | N32: Not started
A33: 29 | B33: Prudential (PACS) | C33: Prudential | D33: High | E33: BD-W1 High | F33: ("AI governance" OR "responsible AI" OR "data governance" OR "chief data officer" OR "head of compliance" OR "AI ethics") | G33: ("talent acquisition" OR recruiter OR "recruitment" OR HRBP OR "head of HR" OR "people partner" OR "human resources") | I33: Open search | J33: T3-EN | K33: EN | N33: Not started
A34: 30 | B34: Manus (Butterfly Effect) — now Meta | C34: Manus | D34: Medium-High | E34: BD-W1 High | F34: (CISO OR "head of security" OR "security engineering" OR "AI security" OR "trust and safety" OR "head of cybersecurity" OR CTO OR "VP engineering" OR "head of engineering" OR "engineering director" OR "engineering manager") | G34: ("talent acquisition" OR recruiter OR "recruitment" OR HRBP OR "head of HR" OR "people partner" OR "human resources") | H34: (founder OR "co-founder" OR CEO) | I34: Open search | J34: T2-CN | K34: CN (EN if local hire) | N34: Not started
A35: 31 | B35: Genspark (MainFunc) | C35: Genspark | D35: Medium-High | E35: BD-W1 High | F35: ("head of data" OR "data engineering manager" OR "director of data" OR "data platform" OR "head of data engineering" OR "chief data officer" OR CTO OR "VP engineering" OR "head of engineering" OR "engineering director" OR "engineering manager") | G35: ("talent acquisition" OR recruiter OR "recruitment" OR HRBP OR "head of HR" OR "people partner" OR "human resources") | H35: (founder OR "co-founder" OR CEO) | I35: Open search | J35: T2-CN | K35: CN (EN if local hire) | N35: Not started
A36: 32 | B36: Simular | C36: Simular | D36: Medium-High | E36: BD-W1 High | F36: (CISO OR "head of security" OR "security engineering" OR "AI security" OR "trust and safety" OR "head of cybersecurity" OR CTO OR "VP engineering" OR "head of engineering" OR "engineering director" OR "engineering manager") | G36: ("talent acquisition" OR recruiter OR "recruitment" OR HRBP OR "head of HR" OR "people partner" OR "human resources") | H36: (founder OR "co-founder" OR CEO) | I36: Open search | J36: T2-EN | K36: EN (CN if Mandarin) | N36: Not started
A37: 33 | B37: Envision Digital | C37: Envision Digital | D37: Medium-High | E37: BD-W1 High | F37: ("head of data" OR "data engineering manager" OR "director of data" OR "data platform" OR "head of data engineering" OR "chief data officer" OR "AI governance" OR "responsible AI" OR "data governance" OR "head of compliance" OR "AI ethics" OR CTO) | G37: ("talent acquisition" OR recruiter OR "recruitment" OR HRBP OR "head of HR" OR "people partner" OR "human resources") | H37: (founder OR "co-founder" OR CEO) | I37: Open search | J37: T2-CN | K37: CN (EN if local hire) | N37: Not started
A38: 34 | B38: Zhipu AI (Z.ai) | C38: Zhipu AI | D38: Medium-High | E38: BD-W1 High | F38: ("head of data" OR "data engineering manager" OR "director of data" OR "data platform" OR "head of data engineering" OR "chief data officer" OR "AI governance" OR "responsible AI" OR "data governance" OR "head of compliance" OR "AI ethics" OR CTO) | G38: ("talent acquisition" OR recruiter OR "recruitment" OR HRBP OR "head of HR" OR "people partner" OR "human resources") | I38: Open search | J38: T2-CN | K38: CN (EN if local hire) | N38: Not started
A39: 35 | B39: Bigo Technology (JOYY) | C39: Bigo Technology | D39: Medium-High | E39: BD-W1 High | F39: ("head of data" OR "data engineering manager" OR "director of data" OR "data platform" OR "head of data engineering" OR "chief data officer" OR CISO OR "head of security" OR "security engineering" OR "AI security" OR "trust and safety" OR "head of cybersecurity") | G39: ("talent acquisition" OR recruiter OR "recruitment" OR HRBP OR "head of HR" OR "people partner" OR "human resources") | I39: Open search | J39: T1-CN | K39: CN (EN if local hire) | N39: Not started
A40: 36 | B40: FinVolution Group | C40: FinVolution Group | D40: Medium-High | E40: BD-W1 High | F40: ("head of data" OR "data engineering manager" OR "director of data" OR "data platform" OR "head of data engineering" OR "chief data officer" OR "model risk" OR "head of risk" OR "chief risk officer" OR "risk analytics" OR "fraud" OR "model validation") | G40: ("talent acquisition" OR recruiter OR "recruitment" OR HRBP OR "head of HR" OR "people partner" OR "human resources") | I40: Open search | J40: T3-CN | K40: CN (EN if local hire) | N40: Not started
A41: 37 | B41: SUNRATE | C41: SUNRATE | D41: Medium-High | E41: BD-W1 High | F41: ("head of data" OR "data engineering manager" OR "director of data" OR "data platform" OR "head of data engineering" OR "chief data officer" OR "AI governance" OR "responsible AI" OR "data governance" OR "head of compliance" OR "AI ethics" OR "model risk") | G41: ("talent acquisition" OR recruiter OR "recruitment" OR HRBP OR "head of HR" OR "people partner" OR "human resources") | I41: Open search | J41: T3-EN | K41: EN (CN if Mandarin) | N41: Not started
A42: 38 | B42: OKX Singapore | C42: OKX | D42: Medium-High | E42: BD-W1 High | F42: ("head of data" OR "data engineering manager" OR "director of data" OR "data platform" OR "head of data engineering" OR "chief data officer") | G42: ("talent acquisition" OR recruiter OR "recruitment" OR HRBP OR "head of HR" OR "people partner" OR "human resources") | H42: (founder OR "co-founder" OR CEO) | I42: Open search | J42: T1-CN | K42: CN (EN if local hire) | N42: Not started
A43: 39 | B43: Bitdeer | C43: Bitdeer | D43: Medium-High | E43: BD-W1 High | F43: ("head of data" OR "data engineering manager" OR "director of data" OR "data platform" OR "head of data engineering" OR "chief data officer" OR CISO OR "head of security" OR "security engineering" OR "AI security" OR "trust and safety" OR "head of cybersecurity") | G43: ("talent acquisition" OR recruiter OR "recruitment" OR HRBP OR "head of HR" OR "people partner" OR "human resources") | H43: (founder OR "co-founder" OR CEO) | I43: Open search | J43: T1-CN | K43: CN (EN if local hire) | N43: Not started
A44: 40 | B44: PatSnap | C44: PatSnap | D44: Medium-High | E44: BD-W1 High | F44: ("head of data" OR "data engineering manager" OR "director of data" OR "data platform" OR "head of data engineering" OR "chief data officer" OR "AI governance" OR "responsible AI" OR "data governance" OR "head of compliance" OR "AI ethics" OR CTO) | G44: ("talent acquisition" OR recruiter OR "recruitment" OR HRBP OR "head of HR" OR "people partner" OR "human resources") | I44: Open search | J44: T1-EN | K44: EN (CN if Mandarin) | N44: Not started
A45: 41 | B45: Tabcut | C45: Tabcut | D45: Medium | E45: BD-W2 Medium | F45: ("head of data" OR "data engineering manager" OR "director of data" OR "data platform" OR "head of data engineering" OR "chief data officer" OR CTO OR "VP engineering" OR "head of engineering" OR "engineering director" OR "engineering manager") | G45: ("talent acquisition" OR recruiter OR "recruitment" OR HRBP OR "head of HR" OR "people partner" OR "human resources") | H45: (founder OR "co-founder" OR CEO) | I45: Open search | J45: T2-CN | K45: CN (EN if local hire) | N45: Not started
A46: 42 | B46: Agnes AI (SapiensAI) | C46: Agnes AI | D46: Medium | E46: BD-W2 Medium | F46: ("head of data" OR "data engineering manager" OR "director of data" OR "data platform" OR "head of data engineering" OR "chief data officer" OR CTO OR "VP engineering" OR "head of engineering" OR "engineering director" OR "engineering manager") | G46: ("talent acquisition" OR recruiter OR "recruitment" OR HRBP OR "head of HR" OR "people partner" OR "human resources") | H46: (founder OR "co-founder" OR CEO) | I46: Open search | J46: T2-EN | K46: EN (CN if Mandarin) | N46: Not started
A47: 43 | B47: Sapient Intelligence [verify SG team first] | C47: Sapient Intelligence | D47: Medium | E47: BD-W2 Medium | F47: (CTO OR "VP engineering" OR "head of engineering" OR "engineering director" OR "engineering manager") | G47: ("talent acquisition" OR recruiter OR "recruitment" OR HRBP OR "head of HR" OR "people partner" OR "human resources") | H47: (founder OR "co-founder" OR CEO) | I47: Open search | J47: T2-CN | K47: CN (EN if local hire) | N47: Not started
A48: 44 | B48: Skywork AI (Kunlun Tech) [verify SG team first] | C48: Skywork AI | D48: Medium | E48: BD-W2 Medium | F48: ("head of data" OR "data engineering manager" OR "director of data" OR "data platform" OR "head of data engineering" OR "chief data officer" OR CTO OR "VP engineering" OR "head of engineering" OR "engineering director" OR "engineering manager") | G48: ("talent acquisition" OR recruiter OR "recruitment" OR HRBP OR "head of HR" OR "people partner" OR "human resources") | H48: (founder OR "co-founder" OR CEO) | I48: Open search | J48: T2-CN | K48: CN (EN if local hire) | N48: Not started
A49: 45 | B49: WIZ.AI | C49: WIZ.AI | D49: Medium | E49: BD-W2 Medium | F49: ("head of data" OR "data engineering manager" OR "director of data" OR "data platform" OR "head of data engineering" OR "chief data officer" OR CTO OR "VP engineering" OR "head of engineering" OR "engineering director" OR "engineering manager") | G49: ("talent acquisition" OR recruiter OR "recruitment" OR HRBP OR "head of HR" OR "people partner" OR "human resources") | H49: (founder OR "co-founder" OR CEO) | I49: Open search | J49: T2-CN | K49: CN (EN if local hire) | N49: Not started
A50: 46 | B50: Kuaishou — Symphony Tech (SG unit) | C50: Kuaishou | D50: Medium | E50: BD-W2 Medium | F50: ("head of data" OR "data engineering manager" OR "director of data" OR "data platform" OR "head of data engineering" OR "chief data officer" OR "AI governance" OR "responsible AI" OR "data governance" OR "head of compliance" OR "AI ethics" OR CISO) | G50: ("talent acquisition" OR recruiter OR "recruitment" OR HRBP OR "head of HR" OR "people partner" OR "human resources") | I50: Open search | J50: T2-CN | K50: CN (EN if local hire) | N50: Not started
A51: 47 | B51: PixVerse (AIsphere) [verify SG team first] | C51: PixVerse | D51: Medium | E51: BD-W2 Medium | F51: ("head of data" OR "data engineering manager" OR "director of data" OR "data platform" OR "head of data engineering" OR "chief data officer" OR "AI governance" OR "responsible AI" OR "data governance" OR "head of compliance" OR "AI ethics" OR CTO) | G51: ("talent acquisition" OR recruiter OR "recruitment" OR HRBP OR "head of HR" OR "people partner" OR "human resources") | I51: Open search | J51: T2-CN | K51: CN (EN if local hire) | N51: Not started
A52: 48 | B52: Trip.com Group Singapore | C52: Trip.com Group | D52: Medium | E52: BD-W2 Medium | F52: ("head of data" OR "data engineering manager" OR "director of data" OR "data platform" OR "head of data engineering" OR "chief data officer") | G52: ("talent acquisition" OR recruiter OR "recruitment" OR HRBP OR "head of HR" OR "people partner" OR "human resources") | I52: Open search | J52: T1-CN | K52: CN (EN if local hire) | N52: Not started
A53: 49 | B53: Huawei Singapore (Huawei Cloud / Huawei Intl) | C53: Huawei | D53: Medium | E53: BD-W2 Medium | F53: ("head of data" OR "data engineering manager" OR "director of data" OR "data platform" OR "head of data engineering" OR "chief data officer" OR CISO OR "head of security" OR "security engineering" OR "AI security" OR "trust and safety" OR "head of cybersecurity") | G53: ("talent acquisition" OR recruiter OR "recruitment" OR HRBP OR "head of HR" OR "people partner" OR "human resources") | I53: Open search | J53: T1-CN | K53: CN (EN if local hire) | N53: Not started
A54: 50 | B54: Lark (Feishu) International | C54: Lark International | D54: Medium | E54: BD-W2 Medium | F54: ("AI governance" OR "responsible AI" OR "data governance" OR "chief data officer" OR "head of compliance" OR "AI ethics" OR CISO OR "head of security" OR "security engineering" OR "AI security" OR "trust and safety" OR "head of cybersecurity") | G54: ("talent acquisition" OR recruiter OR "recruitment" OR HRBP OR "head of HR" OR "people partner" OR "human resources") | I54: Open search | J54: T1-CN | K54: CN (EN if local hire) | N54: Not started
A55: 51 | B55: BytePlus (ByteDance enterprise cloud) | C55: BytePlus | D55: Medium | E55: BD-W2 Medium | F55: ("head of data" OR "data engineering manager" OR "director of data" OR "data platform" OR "head of data engineering" OR "chief data officer" OR "AI governance" OR "responsible AI" OR "data governance" OR "head of compliance" OR "AI ethics" OR CTO) | G55: ("talent acquisition" OR recruiter OR "recruitment" OR HRBP OR "head of HR" OR "people partner" OR "human resources") | I55: Open search | J55: T1-CN | K55: CN (EN if local hire) | N55: Not started
A56: 52 | B56: Tencent — Level Infinite (games publishing) | C56: Tencent | D56: Medium | E56: BD-W2 Medium | F56: ("head of data" OR "data engineering manager" OR "director of data" OR "data platform" OR "head of data engineering" OR "chief data officer" OR CTO OR "VP engineering" OR "head of engineering" OR "engineering director" OR "engineering manager") | G56: ("talent acquisition" OR recruiter OR "recruitment" OR HRBP OR "head of HR" OR "people partner" OR "human resources") | I56: Open search | J56: T1-CN | K56: CN (EN if local hire) | N56: Not started
A57: 53 | B57: Lazada (Alibaba) | C57: Lazada | D57: Medium | E57: BD-W2 Medium | F57: ("head of data" OR "data engineering manager" OR "director of data" OR "data platform" OR "head of data engineering" OR "chief data officer" OR CTO OR "VP engineering" OR "head of engineering" OR "engineering director" OR "engineering manager") | G57: ("talent acquisition" OR recruiter OR "recruitment" OR HRBP OR "head of HR" OR "people partner" OR "human resources") | I57: Open search | J57: T1-CN | K57: CN (EN if local hire) | N57: Not started
A58: 54 | B58: Keeta (Meituan) — SEA [verify SG team first] | C58: Keeta | D58: Medium | E58: BD-W2 Medium | F58: ("head of data" OR "data engineering manager" OR "director of data" OR "data platform" OR "head of data engineering" OR "chief data officer") | G58: ("talent acquisition" OR recruiter OR "recruitment" OR HRBP OR "head of HR" OR "people partner" OR "human resources") | I58: Open search | J58: T1-CN | K58: CN (EN if local hire) | N58: Not started
A59: 55 | B59: Temu (PDD) — SEA [verify SG team first] | C59: Temu | D59: Medium | E59: BD-W2 Medium | F59: ("head of data" OR "data engineering manager" OR "director of data" OR "data platform" OR "head of data engineering" OR "chief data officer") | G59: ("talent acquisition" OR recruiter OR "recruitment" OR HRBP OR "head of HR" OR "people partner" OR "human resources") | I59: Open search | J59: T1-CN | K59: CN (EN if local hire) | N59: Not started
A60: 56 | B60: PingPong | C60: PingPong | D60: Medium | E60: BD-W2 Medium | F60: ("head of data" OR "data engineering manager" OR "director of data" OR "data platform" OR "head of data engineering" OR "chief data officer" OR "AI governance" OR "responsible AI" OR "data governance" OR "head of compliance" OR "AI ethics") | G60: ("talent acquisition" OR recruiter OR "recruitment" OR HRBP OR "head of HR" OR "people partner" OR "human resources") | I60: Open search | J60: T1-CN | K60: CN (EN if local hire) | N60: Not started
A61: 57 | B61: XTransfer | C61: XTransfer | D61: Medium | E61: BD-W2 Medium | F61: ("head of data" OR "data engineering manager" OR "director of data" OR "data platform" OR "head of data engineering" OR "chief data officer") | G61: ("talent acquisition" OR recruiter OR "recruitment" OR HRBP OR "head of HR" OR "people partner" OR "human resources") | I61: Open search | J61: T1-CN | K61: CN (EN if local hire) | N61: Not started
... A70: 66 | B70: Longbridge Singapore [verify SG team first] | C70: Longbridge | D70: Medium | E70: BD-W2 Medium | F70: ("head of data" OR "data engineering manager" OR "director of data" OR "data platform" OR "head of data engineering" OR "chief data officer" OR "AI governance" OR "responsible AI" OR "data governance" OR "head of compliance" OR "AI ethics" OR "model risk") | G70: ("talent acquisition" OR recruiter OR "recruitment" OR HRBP OR "head of HR" OR "people partner" OR "human resources") | I70: Open search | J70: T3-CN | K70: CN (EN if local hire) | N70: Not started
A71: 67 | B71: Binance Singapore [verify SG team first] | C71: Binance | D71: Medium | E71: BD-W2 Medium | F71: ("head of data" OR "data engineering manager" OR "director of data" OR "data platform" OR "head of data engineering" OR "chief data officer") | G71: ("talent acquisition" OR recruiter OR "recruitment" OR HRBP OR "head of HR" OR "people partner" OR "human resources") | H71: (founder OR "co-founder" OR CEO) | I71: Open search | J71: T1-EN | K71: EN (CN if Mandarin) | N71: Not started
A72: 68 | B72: Matrixport Singapore | C72: Matrixport | D72: Medium | E72: BD-W2 Medium | F72: ("head of data" OR "data engineering manager" OR "director of data" OR "data platform" OR "head of data engineering" OR "chief data officer") | G72: ("talent acquisition" OR recruiter OR "recruitment" OR HRBP OR "head of HR" OR "people partner" OR "human resources") | H72: (founder OR "co-founder" OR CEO) | I72: Open search | J72: T1-CN | K72: CN (EN if local hire) | N72: Not started
A73: 69 | B73: Amber Group Singapore | C73: Amber Group | D73: Medium | E73: BD-W2 Medium | F73: ("head of data" OR "data engineering manager" OR "director of data" OR "data platform" OR "head of data engineering" OR "chief data officer") | G73: ("talent acquisition" OR recruiter OR "recruitment" OR HRBP OR "head of HR" OR "people partner" OR "human resources") | H73: (founder OR "co-founder" OR CEO) | I73: Open search | J73: T1-CN | K73: CN (EN if local hire) | N73: Not started
A74: 70 | B74: Coinhako | C74: Coinhako | D74: Medium | E74: BD-W2 Medium | F74: ("head of data" OR "data engineering manager" OR "director of data" OR "data platform" OR "head of data engineering" OR "chief data officer") | G74: ("talent acquisition" OR recruiter OR "recruitment" OR HRBP OR "head of HR" OR "people partner" OR "human resources") | H74: (founder OR "co-founder" OR CEO) | I74: Open search | J74: T1-EN | K74: EN (CN if Mandarin) | N74: Not started
A75: 71 | B75: Paradex | C75: Paradex | D75: Medium | E75: BD-W2 Medium | F75: ("head of data" OR "data engineering manager" OR "director of data" OR "data platform" OR "head of data engineering" OR "chief data officer") | G75: ("talent acquisition" OR recruiter OR "recruitment" OR HRBP OR "head of HR" OR "people partner" OR "human resources") | H75: (founder OR "co-founder" OR CEO) | I75: Open search | J75: T1-EN | K75: EN | N75: Not started
A76: 72 | B76: Cobo | C76: Cobo | D76: Medium | E76: BD-W2 Medium | F76: ("head of data" OR "data engineering manager" OR "director of data" OR "data platform" OR "head of data engineering" OR "chief data officer" OR CISO OR "head of security" OR "security engineering" OR "AI security" OR "trust and safety" OR "head of cybersecurity") | G76: ("talent acquisition" OR recruiter OR "recruitment" OR HRBP OR "head of HR" OR "people partner" OR "human resources") | H76: (founder OR "co-founder" OR CEO) | I76: Open search | J76: T1-CN | K76: CN (EN if local hire) | N76: Not started
A77: 73 | B77: Antalpha | C77: Antalpha | D77: Medium | E77: BD-W2 Medium | F77: ("head of data" OR "data engineering manager" OR "director of data" OR "data platform" OR "head of data engineering" OR "chief data officer" OR "model risk" OR "head of risk" OR "chief risk officer" OR "risk analytics" OR "fraud" OR "model validation") | G77: ("talent acquisition" OR recruiter OR "recruitment" OR HRBP OR "head of HR" OR "people partner" OR "human resources") | H77: (founder OR "co-founder" OR CEO) | I77: Open search | J77: T1-CN | K77: CN (EN if local hire) | N77: Not started
A78: 74 | B78: WeRide | C78: WeRide | D78: Medium | E78: BD-W2 Medium | F78: ("head of data" OR "data engineering manager" OR "director of data" OR "data platform" OR "head of data engineering" OR "chief data officer" OR "model risk" OR "head of risk" OR "chief risk officer" OR "risk analytics" OR "fraud" OR "model validation") | G78: ("talent acquisition" OR recruiter OR "recruitment" OR HRBP OR "head of HR" OR "people partner" OR "human resources") | H78: (founder OR "co-founder" OR CEO) | I78: Open search | J78: T1-CN | K78: CN (EN if local hire) | N78: Not started
A79: 75 | B79: Pony.ai | C79: Pony.ai | D79: Medium | E79: BD-W2 Medium | F79: ("head of data" OR "data engineering manager" OR "director of data" OR "data platform" OR "head of data engineering" OR "chief data officer" OR "model risk" OR "head of risk" OR "chief risk officer" OR "risk analytics" OR "fraud" OR "model validation") | G79: ("talent acquisition" OR recruiter OR "recruitment" OR HRBP OR "head of HR" OR "people partner" OR "human resources") | H79: (founder OR "co-founder" OR CEO) | I79: Open search | J79: T1-CN | K79: CN (EN if local hire) | N79: Not started
A80: 76 | B80: AgiBot | C80: AgiBot | D80: Medium | E80: BD-W2 Medium | F80: (CTO OR "VP engineering" OR "head of engineering" OR "engineering director" OR "engineering manager") | G80: ("talent acquisition" OR recruiter OR "recruitment" OR HRBP OR "head of HR" OR "people partner" OR "human resources") | H80: (founder OR "co-founder" OR CEO) | I80: Open search | J80: T1-CN | K80: CN (EN if local hire) | N80: Not started
A81: 77 | B81: NetEase Games Singapore | C81: NetEase Games | D81: Medium | E81: BD-W2 Medium | F81: ("head of data" OR "data engineering manager" OR "director of data" OR "data platform" OR "head of data engineering" OR "chief data officer") | G81: ("talent acquisition" OR recruiter OR "recruitment" OR HRBP OR "head of HR" OR "people partner" OR "human resources") | I81: Open search | J81: T1-CN | K81: CN (EN if local hire) | N81: Not started
A82: 78 | B82: Razer | C82: Razer | D82: Medium | E82: BD-W2 Medium | F82: ("head of data" OR "data engineering manager" OR "director of data" OR "data platform" OR "head of data engineering" OR "chief data officer") | G82: ("talent acquisition" OR recruiter OR "recruitment" OR HRBP OR "head of HR" OR "people partner" OR "human resources") | I82: Open search | J82: T1-EN | K82: EN (CN if Mandarin) | N82: Not started
A83: 79 | B83: Shoplazza (店匠科技) | C83: Shoplazza | D83: Medium | E83: BD-W2 Medium | F83: ("head of data" OR "data engineering manager" OR "director of data" OR "data platform" OR "head of data engineering" OR "chief data officer") | G83: ("talent acquisition" OR recruiter OR "recruitment" OR HRBP OR "head of HR" OR "people partner" OR "human resources") | I83: Open search | J83: T1-CN | K83: CN (EN if local hire) | N83: Not started
A84: 80 | B84: (Long-tail blue ocean) Singapore-based Chinese cross-border e-commerce / DTC teams | C84: Singapore-based Chinese cross-border e-commerce OR DTC teams | D84: Medium | E84: BD-W2 Medium | F84: ("head of data" OR "data engineering manager" OR "director of data" OR "data platform" OR "head of data engineering" OR "chief data officer") | G84: ("talent acquisition" OR recruiter OR "recruitment" OR HRBP OR "head of HR" OR "people partner" OR "human resources") | I84: Open search | J84: T1-CN | K84: CN (EN if local hire) | N84: Not started
A85: 81 | B85: GoodNotes | C85: GoodNotes | D85: Medium | E85: BD-W2 Medium | F85: ("head of data" OR "data engineering manager" OR "director of data" OR "data platform" OR "head of data engineering" OR "chief data officer") | G85: ("talent acquisition" OR recruiter OR "recruitment" OR HRBP OR "head of HR" OR "people partner" OR "human resources") | I85: Open search | J85: T1-EN | K85: EN (CN if Mandarin) | N85: Not started
A86: 82 | B86: Carousell | C86: Carousell | D86: Medium | E86: BD-W2 Medium | F86: ("head of data" OR "data engineering manager" OR "director of data" OR "data platform" OR "head of data engineering" OR "chief data officer" OR CTO OR "VP engineering" OR "head of engineering" OR "engineering director" OR "engineering manager") | G86: ("talent acquisition" OR recruiter OR "recruitment" OR HRBP OR "head of HR" OR "people partner" OR "human resources") | I86: Open search | J86: T1-EN | K86: EN (CN if Mandarin) | N86: Not started
A87: 83 | B87: Ninja Van | C87: Ninja Van | D87: Medium | E87: BD-W2 Medium | F87: ("head of data" OR "data engineering manager" OR "director of data" OR "data platform" OR "head of data engineering" OR "chief data officer" OR CTO OR "VP engineering" OR "head of engineering" OR "engineering director" OR "engineering manager") | G87: ("talent acquisition" OR recruiter OR "recruitment" OR HRBP OR "head of HR" OR "people partner" OR "human resources") | I87: Open search | J87: T1-EN | K87: EN (CN if Mandarin) | N87: Not started
A88: 84 | B88: Bank of China Singapore | C88: Bank of China | D88: Medium | E88: BD-W2 Medium | F88: ("head of data" OR "data engineering manager" OR "director of data" OR "data platform" OR "head of data engineering" OR "chief data officer" OR "AI governance" OR "responsible AI" OR "data governance" OR "head of compliance" OR "AI ethics") | G88: ("talent acquisition" OR recruiter OR "recruitment" OR HRBP OR "head of HR" OR "people partner" OR "human resources") | I88: Open search | J88: T3-CN | K88: CN (EN if local hire) | N88: Not started
A89: 85 | B89: ICBC Singapore | C89: ICBC | D89: Medium | E89: BD-W2 Medium | F89: ("head of data" OR "data engineering manager" OR "director of data" OR "data platform" OR "head of data engineering" OR "chief data officer" OR "AI governance" OR "responsible AI" OR "data governance" OR "head of compliance" OR "AI ethics") | G89: ("talent acquisition" OR recruiter OR "recruitment" OR HRBP OR "head of HR" OR "people partner" OR "human resources") | I89: Open search | J89: T3-CN | K89: CN (EN if local hire) | N89: Not started
A90: 86 | B90: China Construction Bank (CCB) Singapore | C90: China Construction Bank | D90: Medium | E90: BD-W2 Medium | F90: ("head of data" OR "data engineering manager" OR "director of data" OR "data platform" OR "head of data engineering" OR "chief data officer" OR "AI governance" OR "responsible AI" OR "data governance" OR "head of compliance" OR "AI ethics") | G90: ("talent acquisition" OR recruiter OR "recruitment" OR HRBP OR "head of HR" OR "people partner" OR "human resources") | I90: Open search | J90: T3-CN | K90: CN (EN if local hire) | N90: Not started
A91: 87 | B91: Agricultural Bank of China (ABC) Singapore | C91: Agricultural Bank of China | D91: Medium | E91: BD-W2 Medium | F91: ("head of data" OR "data engineering manager" OR "director of data" OR "data platform" OR "head of data engineering" OR "chief data officer" OR "AI governance" OR "responsible AI" OR "data governance" OR "head of compliance" OR "AI ethics") | G91: ("talent acquisition" OR recruiter OR "recruitment" OR HRBP OR "head of HR" OR "people partner" OR "human resources") | I91: Open search | J91: T3-CN | K91: CN (EN if local hire) | N91: Not started
A92: 88 | B92: China Merchants Bank Singapore | C92: China Merchants Bank | D92: Medium | E92: BD-W2 Medium | F92: ("head of data" OR "data engineering manager" OR "director of data" OR "data platform" OR "head of data engineering" OR "chief data officer") | G92: ("talent acquisition" OR recruiter OR "recruitment" OR HRBP OR "head of HR" OR "people partner" OR "human resources") | I92: Open search | J92: T3-CN | K92: CN (EN if local hire) | N92: Not started
... A137: 133 | B137: Argus Media | C137: Argus Media | D137: Medium | E137: BD-W2 Medium | F137: ("head of data" OR "data engineering manager" OR "director of data" OR "data platform" OR "head of data engineering" OR "chief data officer") | G137: ("talent acquisition" OR recruiter OR "recruitment" OR HRBP OR "head of HR" OR "people partner" OR "human resources") | I137: Open search | J137: T1-EN | K137: EN | N137: Not started
A138: 134 | B138: AI Rudder [verify SG team first] | C138: AI Rudder | D138: Low-Medium | E138: BD-W3 Long-tail | F138: ("head of data" OR "data engineering manager" OR "director of data" OR "data platform" OR "head of data engineering" OR "chief data officer" OR CTO OR "VP engineering" OR "head of engineering" OR "engineering director" OR "engineering manager") | G138: ("talent acquisition" OR recruiter OR "recruitment" OR HRBP OR "head of HR" OR "people partner" OR "human resources") | H138: (founder OR "co-founder" OR CEO) | I138: Open search | J138: T2-EN | K138: EN (CN if Mandarin) | N138: Not started
A139: 135 | B139: Green Link Digital Bank | C139: Green Link Digital Bank | D139: Low-Medium | E139: BD-W3 Long-tail | F139: ("head of data" OR "data engineering manager" OR "director of data" OR "data platform" OR "head of data engineering" OR "chief data officer" OR "AI governance" OR "responsible AI" OR "data governance" OR "head of compliance" OR "AI ethics" OR "model risk") | G139: ("talent acquisition" OR recruiter OR "recruitment" OR HRBP OR "head of HR" OR "people partner" OR "human resources") | I139: Open search | J139: T3-CN | K139: CN (EN if local hire) | N139: Not started
A140: 136 | B140: Trust Bank (StanChart–FairPrice) | C140: Trust Bank | D140: Low-Medium | E140: BD-W3 Long-tail | F140: ("head of data" OR "data engineering manager" OR "director of data" OR "data platform" OR "head of data engineering" OR "chief data officer" OR "AI governance" OR "responsible AI" OR "data governance" OR "head of compliance" OR "AI ethics" OR "model risk") | G140: ("talent acquisition" OR recruiter OR "recruitment" OR HRBP OR "head of HR" OR "people partner" OR "human resources") | I140: Open search | J140: T3-EN | K140: EN | N140: Not started
A141: 137 | B141: LexinFintech [verify SG team first] | C141: LexinFintech | D141: Low-Medium | E141: BD-W3 Long-tail | F141: ("head of data" OR "data engineering manager" OR "director of data" OR "data platform" OR "head of data engineering" OR "chief data officer" OR "model risk" OR "head of risk" OR "chief risk officer" OR "risk analytics" OR "fraud" OR "model validation") | G141: ("talent acquisition" OR recruiter OR "recruitment" OR HRBP OR "head of HR" OR "people partner" OR "human resources") | I141: Open search | J141: T3-CN | K141: CN (EN if local hire) | N141: Not started
A142: 138 | B142: Jiayin Group [verify SG team first] | C142: Jiayin Group | D142: Low-Medium | E142: BD-W3 Long-tail | F142: ("head of data" OR "data engineering manager" OR "director of data" OR "data platform" OR "head of data engineering" OR "chief data officer" OR "model risk" OR "head of risk" OR "chief risk officer" OR "risk analytics" OR "fraud" OR "model validation") | G142: ("talent acquisition" OR recruiter OR "recruitment" OR HRBP OR "head of HR" OR "people partner" OR "human resources") | I142: Open search | J142: T3-CN | K142: CN (EN if local hire) | N142: Not started
A143: 139 | B143: UnionPay International (Singapore) [verify SG team first] | C143: UnionPay International | D143: Low-Medium | E143: BD-W3 Long-tail | F143: ("head of data" OR "data engineering manager" OR "director of data" OR "data platform" OR "head of data engineering" OR "chief data officer" OR CISO OR "head of security" OR "security engineering" OR "AI security" OR "trust and safety" OR "head of cybersecurity") | G143: ("talent acquisition" OR recruiter OR "recruitment" OR HRBP OR "head of HR" OR "people partner" OR "human resources") | I143: Open search | J143: T3-CN | K143: CN (EN if local hire) | N143: Not started
A144: 140 | B144: Bitget [verify SG team first] | C144: Bitget | D144: Low-Medium | E144: BD-W3 Long-tail | F144: ("head of data" OR "data engineering manager" OR "director of data" OR "data platform" OR "head of data engineering" OR "chief data officer" OR CISO OR "head of security" OR "security engineering" OR "AI security" OR "trust and safety" OR "head of cybersecurity") | G144: ("talent acquisition" OR recruiter OR "recruitment" OR HRBP OR "head of HR" OR "people partner" OR "human resources") | H144: (founder OR "co-founder" OR CEO) | I144: Open search | J144: T1-EN | K144: EN (CN if Mandarin) | N144: Not started
A145: 141 | B145: Crypto.com | C145: Crypto.com | D145: Low-Medium | E145: BD-W3 Long-tail | F145: ("head of data" OR "data engineering manager" OR "director of data" OR "data platform" OR "head of data engineering" OR "chief data officer" OR CISO OR "head of security" OR "security engineering" OR "AI security" OR "trust and safety" OR "head of cybersecurity") | G145: ("talent acquisition" OR recruiter OR "recruitment" OR HRBP OR "head of HR" OR "people partner" OR "human resources") | H145: (founder OR "co-founder" OR CEO) | I145: Open search | J145: T1-EN | K145: EN | N145: Not started
A146: 142 | B146: imToken | C146: imToken | D146: Low-Medium | E146: BD-W3 Long-tail | F146: (CISO OR "head of security" OR "security engineering" OR "AI security" OR "trust and safety" OR "head of cybersecurity" OR CTO OR "VP engineering" OR "head of engineering" OR "engineering director" OR "engineering manager") | G146: ("talent acquisition" OR recruiter OR "recruitment" OR HRBP OR "head of HR" OR "people partner" OR "human resources") | H146: (founder OR "co-founder" OR CEO) | I146: Open search | J146: T1-CN | K146: CN (EN if local hire) | N146: Not started
A147: 143 | B147: Unitree Robotics [verify SG team first] | C147: Unitree Robotics | D147: Low-Medium | E147: BD-W3 Long-tail | F147: (CTO OR "VP engineering" OR "head of engineering" OR "engineering director" OR "engineering manager") | G147: ("talent acquisition" OR recruiter OR "recruitment" OR HRBP OR "head of HR" OR "people partner" OR "human resources") | H147: (founder OR "co-founder" OR CEO) | I147: Open search | J147: T1-CN | K147: CN (EN if local hire) | N147: Not started
A148: 144 | B148: Geek+ | C148: Geek+ | D148: Low-Medium | E148: BD-W3 Long-tail | F148: ("head of data" OR "data engineering manager" OR "director of data" OR "data platform" OR "head of data engineering" OR "chief data officer" OR CTO OR "VP engineering" OR "head of engineering" OR "engineering director" OR "engineering manager") | G148: ("talent acquisition" OR recruiter OR "recruitment" OR HRBP OR "head of HR" OR "people partner" OR "human resources") | H148: (founder OR "co-founder" OR CEO) | I148: Open search | J148: T1-CN | K148: CN (EN if local hire) | N148: Not started
A149: 145 | B149: IGG Singapore [verify SG team first] | C149: IGG | D149: Low-Medium | E149: BD-W3 Long-tail | F149: ("head of data" OR "data engineering manager" OR "director of data" OR "data platform" OR "head of data engineering" OR "chief data officer") | G149: ("talent acquisition" OR recruiter OR "recruitment" OR HRBP OR "head of HR" OR "people partner" OR "human resources") | I149: Open search | J149: T1-CN | K149: CN (EN if local hire) | N149: Not started
A150: 146 | B150: FunPlus Singapore [verify SG team first] | C150: FunPlus | D150: Low-Medium | E150: BD-W3 Long-tail | F150: ("head of data" OR "data engineering manager" OR "director of data" OR "data platform" OR "head of data engineering" OR "chief data officer") | G150: ("talent acquisition" OR recruiter OR "recruitment" OR HRBP OR "head of HR" OR "people partner" OR "human resources") | I150: Open search | J150: T1-CN | K150: CN (EN if local hire) | N150: Not started
A151: 147 | B151: Lilith Games Singapore [verify SG team first] | C151: Lilith Games | D151: Low-Medium | E151: BD-W3 Long-tail | F151: ("head of data" OR "data engineering manager" OR "director of data" OR "data platform" OR "head of data engineering" OR "chief data officer") | G151: ("talent acquisition" OR recruiter OR "recruitment" OR HRBP OR "head of HR" OR "people partner" OR "human resources") | I151: Open search | J151: T1-CN | K151: CN (EN if local hire) | N151: Not started
A152: 148 | B152: Moonton [verify SG team first] | C152: Moonton | D152: Low-Medium | E152: BD-W3 Long-tail | F152: ("head of data" OR "data engineering manager" OR "director of data" OR "data platform" OR "head of data engineering" OR "chief data officer" OR CTO OR "VP engineering" OR "head of engineering" OR "engineering director" OR "engineering manager") | G152: ("talent acquisition" OR recruiter OR "recruitment" OR HRBP OR "head of HR" OR "people partner" OR "human resources") | I152: Open search | J152: T1-CN | K152: CN (EN if local hire) | N152: Not started
A153: 149 | B153: Shopline | C153: Shopline | D153: Low-Medium | E153: BD-W3 Long-tail | F153: ("head of data" OR "data engineering manager" OR "director of data" OR "data platform" OR "head of data engineering" OR "chief data officer" OR CTO OR "VP engineering" OR "head of engineering" OR "engineering director" OR "engineering manager") | G153: ("talent acquisition" OR recruiter OR "recruitment" OR HRBP OR "head of HR" OR "people partner" OR "human resources") | I153: Open search | J153: T1-EN | K153: EN (CN if Mandarin) | N153: Not started
...

Sheet InMail Templates
A1: InMail Templates — save each one in Recruiter (Settings → Templates, or the 'Templates' menu when composing)
A2: {firstName} / {company} / {senderFirstName}: replace with Recruiter's own variables via the 'Insert' menu in the template editor. [Square brackets] = edit per message (signal, role, X). LinkedIn limits: subject ≤200 characters, body ≤1,900; columns F-G check this.
A4: ID | B4: Use for | C4: Lang | D4: Subject | E4: Body | F4: Subject chars | G4: Body chars
A5: T1-CN | B5: General — hiring manager | C5: CN | D5: 新加坡{company}技术团队招聘 — 一位工程师出身的猎头 | E5: {firstName}您好， 我是{senderFirstName}，在新加坡做技术猎头，之前做了[X]年软件工程师，现在专注 Data Engineering、AI Governance、AI Security / Risk 和软件工程方向。 注意到{company}最近[具体信号]。中资企业在新加坡招技术人才，常见难点是总部不太了解本地薪酬行情，合适的候选人又大多不主动看机会。我可以用中文和总部沟通，用英文对接本地候选人，并先做一轮技术筛选。 您这边近期在新加坡有没有比较难招的技术岗位？方便的话约15分钟聊聊，我也可以先分享这几个方向的新加坡薪酬行情供您参考。 谢谢！ {senderFirstName} | F5: =LEN(D5) -> 31 | G5: =LEN(E5) -> 311
A6: T1-EN | B6: General — hiring manager | C6: EN | D6: Hard-to-fill tech roles at {company} Singapore? | E6: Hi {firstName}, I'm {senderFirstName}, a Singapore tech recruiter and former software engineer ([X] years). I focus on data engineering, AI governance, AI security / risk and software engineering. I noticed {company} recently [signal]. The strongest people for these roles rarely apply to job ads, so I reach them directly and screen technically before anyone reaches your team. Is there a role on your Singapore roadmap that's proving hard to fill? Happy to share current salary benchmarks over a 15-minute call. Best, {senderFirstName} | F6: =LEN(D6) -> 47 | G6: =LEN(E6) -> 541
A7: T2-CN | B7: Funded / scaling AI startup — founder or CTO | C7: CN | D7: 恭喜{company}[融资/新总部] — 新加坡团队扩张 | E7: {firstName}您好，恭喜{company}[完成X轮融资 / 新加坡总部开业]！ 这个阶段通常是招人最快、但招聘体系还没搭起来的时候。我是工程师出身的猎头，专注 AI / Agent 工程、数据工程和 AI 安全方向，可以先替你们做技术筛选，节省团队的面试时间。 如果[岗位]在计划里，我可以在[X]个工作日内先发2-3份匿名候选人简介，合不合适您来判断，不合适不收费。方便聊15分钟吗？ {senderFirstName} | F7: =LEN(D7) -> 29 | G7: =LEN(E7) -> 219
A8: T2-EN | B8: Funded / scaling AI startup — founder or CTO | C8: EN | D8: Congrats on [milestone] — scaling {company} in Singapore | E8: Hi {firstName}, congratulations on [milestone]! This is usually when hiring moves fastest but internal recruiting isn't in place yet. I'm an ex-engineer recruiter focused on AI / agent engineering, data engineering and AI security, so I screen technically before anyone reaches your team. If [role] is on your plan, I can send 2-3 anonymised profiles within [X] working days. You judge the fit, and there's no fee unless you hire. Open to a 15-minute call? {senderFirstName} | F8: =LEN(D8) -> 56 | G8: =LEN(E8) -> 477
A9: T3-CN | B9: MAS-regulated FI — AI governance / AI risk | C9: CN | D9: MAS《AI风险管理指引》— {company}新加坡的人才准备 | E9: {firstName}您好， MAS 于10月7日发布了《AI风险管理指引》，适用于所有持牌金融机构，过渡期约12个月，涵盖AI使用清单、风险评估、模型验证和治理责任。 既懂ML模型又懂监管的人在新加坡非常稀缺，接下来一年银行、券商和保险都会集中招聘。我专注 AI Governance / AI Risk / 数据方向的招聘，可以先给您一页简要说明：新规对人员配置的影响和市场薪酬，方便您向总部汇报。 方便约个时间聊聊吗？ {senderFirstName} | F9: =LEN(D9) -> 32 | G9: =LEN(E9) -> 234
A10: T3-EN | B10: MAS-regulated FI — AI governance / AI risk | C10: EN | D10: MAS AI Risk Guidelines — staffing at {company} | E10: Hi {firstName}, MAS issued its AI Risk Management Guidelines on 7 October, with a transition period of roughly 12 months covering AI inventory, risk assessment, model validation and accountability. People who understand both ML models and regulation are scarce in Singapore, and most FIs will be hiring for these roles over the next year. I specialise in AI governance, AI risk and data hiring. I'd be glad to share a one-page brief on what the guidelines mean for headcount, plus current market rates. Would a short call be useful? {senderFirstName} | F10: =LEN(D10) -> 46 | G10: =LEN(E10) -> 554
A11: T4-CN | B11: AI security — CISO / security lead | C11: CN | D11: AI / Agent 安全人才 — 新加坡 | E11: {firstName}您好， AI Agent 带来的攻击面（prompt injection、工具调用权限、数据外泄）和传统应用安全很不一样，真正做过 LLM / Agent 安全的人在新加坡很少。 我是工程师出身的猎头，专门在做 AI Security 这个细分方向。如果{company}在新加坡有相关岗位，或者在规划这块能力，我可以先发几份匿名候选人简介给您参考。 方便的话回复一下就好。 {senderFirstName} | F11: =LEN(D11) -> 21 | G11: =LEN(E11) -> 220
A12: T4-EN | B12: AI security — CISO / security lead | C12: EN | D12: AI / agent security talent in Singapore | E12: Hi {firstName}, Securing AI agents (prompt injection, tool permissions, data exfiltration) is a different skill set from traditional appsec, and few people in Singapore have done it hands-on. As an ex-engineer, I focus on this niche. If {company} is hiring for it in Singapore, or planning to build the capability, I can send a few anonymised profiles for reference. Just reply if useful. {senderFirstName} | F12: =LEN(D12) -> 39 | G12: =LEN(E12) -> 410
A13: T5-CN | B13: Quant / trading — head of tech or data | C13: CN | D13: 新加坡量化数据工程人才 | E13: {firstName}您好， 我是{senderFirstName}，在新加坡做技术猎头，工程师出身，专注量化方向的数据工程和基础设施岗位（行情数据、另类数据、研究平台）。 看到{company}[在新加坡设办公室 / 扩团队]。这类候选人基本不主动看机会，我主要靠定向挖掘，能找到在新加坡本地、做过量化数据基础设施的人。 如果近期有相关岗位，我可以先发2-3份匿名简介，您看是否对口。 {senderFirstName} | F13: =LEN(D13) -> 11 | G13: =LEN(E13) -> 215
A14: T5-EN | B14: Quant / trading — head of tech or data | C14: EN | D14: Quant data engineering talent — Singapore | E14: Hi {firstName}, I'm {senderFirstName}, an ex-engineer tech recruiter in Singapore focused on quant data engineering and infrastructure (market data, alt-data, research platforms). These candidates are almost never on the market, so I find them through targeted headhunting, with a focus on people already in Singapore. If {company} has a data or infra role open, I can send 2-3 anonymised profiles so you can judge the fit. {senderFirstName} | F14: =LEN(D14) -> 41 | G14: =LEN(E14) -> 445
A15: T6-CN | B15: TA / HR — partnership | C15: CN | D15: 新加坡技术招聘合作 — {company} | E15: {firstName}您好， 我是{senderFirstName}，新加坡技术猎头，工程师出身，专注 AI / 数据 / AI 安全与风控方向。 了解到{company}在新加坡[扩张/招聘]。很多团队会把这类难招的技术岗位交给专精的外部顾问补充，我可以先接1-2个最难的岗位，用实际结果来证明价值。 想问一下贵司目前和猎头合作的流程（供应商名单或条款）是怎样的？方便的话约15分钟聊聊。 {senderFirstName} | F15: =LEN(D15) -> 21 | G15: =LEN(E15) -> 217
A16: T6-EN | B16: TA / HR — partnership | C16: EN | D16: Supporting {company}'s tech hiring in Singapore | E16: Hi {firstName}, I'm {senderFirstName}, an ex-engineer tech recruiter in Singapore focused on AI, data, AI security and AI risk roles. I understand {company} is [growing / hiring] in Singapore. Many TA teams bring in a specialist for their hardest technical roles, and I'd be happy to start with one or two of yours and prove value on results. Could you share how you work with agencies (PSL, terms)? Happy to set up a quick 15-minute call. {senderFirstName} | F16: =LEN(D16) -> 47 | G16: =LEN(E16) -> 461
... A20: F2-EN | B20: Follow-up #2 (day 14) — last | C20: EN | D20: Closing the loop | E20: Hi {firstName}, closing the loop here. If {company} ever needs help with AI or data hiring in Singapore, I'm happy to help, and I'll keep you posted on market moves in this space. All the best! {senderFirstName} | F20: =LEN(D20) -> 16 | G20: =LEN(E20) -> 212

Sheet Summary
A1: Summary — counts update automatically from 'Master Target List'
A3: Category | B3: High | C3: Medium-High | D3: Medium | E3: Low-Medium | F3: Low | G3: Radar | H3: Total | I3: of which added in v2/v2.1
A4: AI Startups & Labs (Chinese-founded / SG-relocated) | B4: =COUNTIFS('Master Target List'!$D$5:$D$226,$A4,'Master Target List'!$O$5:$O$226,"High") -> 4 | C4: =COUNTIFS('Master Target List'!$D$5:$D$226,$A4,'Master Target List'!$O$5:$O$226,"Medium-High") -> 4 | D4: =COUNTIFS('Master Target List'!$D$5:$D$226,$A4,'Master Target List'!$O$5:$O$226,"Medium") -> 5 | E4: =COUNTIFS('Master Target List'!$D$5:$D$226,$A4,'Master Target List'!$O$5:$O$226,"Low-Medium") -> 1 | F4: =COUNTIFS('Master Target List'!$D$5:$D$226,$A4,'Master Target List'!$O$5:$O$226,"Low") -> 1 | G4: =COUNTIFS('Master Target List'!$D$5:$D$226,$A4,'Master Target List'!$O$5:$O$226,"Radar") -> 1 | H4: =SUM(B4:G4) -> 16 | I4: =COUNTIFS('Master Target List'!$D$5:$D$226,$A4,'Master Target List'!$R$5:$R$226,"<>v1") -> 16
A5: Chinese Foundation-Model Firms Going Abroad | B5: =COUNTIFS('Master Target List'!$D$5:$D$226,$A5,'Master Target List'!$O$5:$O$226,"High") -> 2 | C5: =COUNTIFS('Master Target List'!$D$5:$D$226,$A5,'Master Target List'!$O$5:$O$226,"Medium-High") -> 1 | D5: =COUNTIFS('Master Target List'!$D$5:$D$226,$A5,'Master Target List'!$O$5:$O$226,"Medium") -> 2 | E5: =COUNTIFS('Master Target List'!$D$5:$D$226,$A5,'Master Target List'!$O$5:$O$226,"Low-Medium") -> 0 | F5: =COUNTIFS('Master Target List'!$D$5:$D$226,$A5,'Master Target List'!$O$5:$O$226,"Low") -> 0 | G5: =COUNTIFS('Master Target List'!$D$5:$D$226,$A5,'Master Target List'!$O$5:$O$226,"Radar") -> 4 | H5: =SUM(B5:G5) -> 9 | I5: =COUNTIFS('Master Target List'!$D$5:$D$226,$A5,'Master Target List'!$R$5:$R$226,"<>v1") -> 9
A6: Tech Giants (Regional / Global HQ) | B6: =COUNTIFS('Master Target List'!$D$5:$D$226,$A6,'Master Target List'!$O$5:$O$226,"High") -> 8 | C6: =COUNTIFS('Master Target List'!$D$5:$D$226,$A6,'Master Target List'!$O$5:$O$226,"Medium-High") -> 1 | D6: =COUNTIFS('Master Target List'!$D$5:$D$226,$A6,'Master Target List'!$O$5:$O$226,"Medium") -> 8 | E6: =COUNTIFS('Master Target List'!$D$5:$D$226,$A6,'Master Target List'!$O$5:$O$226,"Low-Medium") -> 0 | F6: =COUNTIFS('Master Target List'!$D$5:$D$226,$A6,'Master Target List'!$O$5:$O$226,"Low") -> 2 | G6: =COUNTIFS('Master Target List'!$D$5:$D$226,$A6,'Master Target List'!$O$5:$O$226,"Radar") -> 4 | H6: =SUM(B6:G6) -> 23 | I6: =COUNTIFS('Master Target List'!$D$5:$D$226,$A6,'Master Target List'!$R$5:$R$226,"<>v1") -> 16
A7: Fintech / Payments / Digital Banks | B7: =COUNTIFS('Master Target List'!$D$5:$D$226,$A7,'Master Target List'!$O$5:$O$226,"High") -> 1 | C7: =COUNTIFS('Master Target List'!$D$5:$D$226,$A7,'Master Target List'!$O$5:$O$226,"Medium-High") -> 2 | D7: =COUNTIFS('Master Target List'!$D$5:$D$226,$A7,'Master Target List'!$O$5:$O$226,"Medium") -> 9 | E7: =COUNTIFS('Master Target List'!$D$5:$D$226,$A7,'Master Target List'!$O$5:$O$226,"Low-Medium") -> 5 | F7: =COUNTIFS('Master Target List'!$D$5:$D$226,$A7,'Master Target List'!$O$5:$O$226,"Low") -> 0 | G7: =COUNTIFS('Master Target List'!$D$5:$D$226,$A7,'Master Target List'!$O$5:$O$226,"Radar") -> 4 | H7: =SUM(B7:G7) -> 21 | I7: =COUNTIFS('Master Target List'!$D$5:$D$226,$A7,'Master Target List'!$R$5:$R$226,"<>v1") -> 18
A8: Online Brokerages / Wealth Platforms | B8: =COUNTIFS('Master Target List'!$D$5:$D$226,$A8,'Master Target List'!$O$5:$O$226,"High") -> 2 | C8: =COUNTIFS('Master Target List'!$D$5:$D$226,$A8,'Master Target List'!$O$5:$O$226,"Medium-High") -> 0 | D8: =COUNTIFS('Master Target List'!$D$5:$D$226,$A8,'Master Target List'!$O$5:$O$226,"Medium") -> 2 | E8: =COUNTIFS('Master Target List'!$D$5:$D$226,$A8,'Master Target List'!$O$5:$O$226,"Low-Medium") -> 0 | F8: =COUNTIFS('Master Target List'!$D$5:$D$226,$A8,'Master Target List'!$O$5:$O$226,"Low") -> 0 | G8: =COUNTIFS('Master Target List'!$D$5:$D$226,$A8,'Master Target List'!$O$5:$O$226,"Radar") -> 0 | H8: =SUM(B8:G8) -> 4 | I8: =COUNTIFS('Master Target List'!$D$5:$D$226,$A8,'Master Target List'!$R$5:$R$226,"<>v1") -> 4
A9: Crypto / Web3 | B9: =COUNTIFS('Master Target List'!$D$5:$D$226,$A9,'Master Target List'!$O$5:$O$226,"High") -> 1 | C9: =COUNTIFS('Master Target List'!$D$5:$D$226,$A9,'Master Target List'!$O$5:$O$226,"Medium-High") -> 2 | D9: =COUNTIFS('Master Target List'!$D$5:$D$226,$A9,'Master Target List'!$O$5:$O$226,"Medium") -> 7 | E9: =COUNTIFS('Master Target List'!$D$5:$D$226,$A9,'Master Target List'!$O$5:$O$226,"Low-Medium") -> 3 | F9: =COUNTIFS('Master Target List'!$D$5:$D$226,$A9,'Master Target List'!$O$5:$O$226,"Low") -> 2 | G9: =COUNTIFS('Master Target List'!$D$5:$D$226,$A9,'Master Target List'!$O$5:$O$226,"Radar") -> 0 | H9: =SUM(B9:G9) -> 15 | I9: =COUNTIFS('Master Target List'!$D$5:$D$226,$A9,'Master Target List'!$R$5:$R$226,"<>v1") -> 8
A10: Robotics / Autonomous Driving | B10: =COUNTIFS('Master Target List'!$D$5:$D$226,$A10,'Master Target List'!$O$5:$O$226,"High") -> 0 | C10: =COUNTIFS('Master Target List'!$D$5:$D$226,$A10,'Master Target List'!$O$5:$O$226,"Medium-High") -> 0 | D10: =COUNTIFS('Master Target List'!$D$5:$D$226,$A10,'Master Target List'!$O$5:$O$226,"Medium") -> 3 | E10: =COUNTIFS('Master Target List'!$D$5:$D$226,$A10,'Master Target List'!$O$5:$O$226,"Low-Medium") -> 2 | F10: =COUNTIFS('Master Target List'!$D$5:$D$226,$A10,'Master Target List'!$O$5:$O$226,"Low") -> 4 | G10: =COUNTIFS('Master Target List'!$D$5:$D$226,$A10,'Master Target List'!$O$5:$O$226,"Radar") -> 2 | H10: =SUM(B10:G10) -> 11 | I10: =COUNTIFS('Master Target List'!$D$5:$D$226,$A10,'Master Target List'!$R$5:$R$226,"<>v1") -> 11
A11: Gaming | B11: =COUNTIFS('Master Target List'!$D$5:$D$226,$A11,'Master Target List'!$O$5:$O$226,"High") -> 1 | C11: =COUNTIFS('Master Target List'!$D$5:$D$226,$A11,'Master Target List'!$O$5:$O$226,"Medium-High") -> 0 | D11: =COUNTIFS('Master Target List'!$D$5:$D$226,$A11,'Master Target List'!$O$5:$O$226,"Medium") -> 2 | E11: =COUNTIFS('Master Target List'!$D$5:$D$226,$A11,'Master Target List'!$O$5:$O$226,"Low-Medium") -> 4 | F11: =COUNTIFS('Master Target List'!$D$5:$D$226,$A11,'Master Target List'!$O$5:$O$226,"Low") -> 0 | G11: =COUNTIFS('Master Target List'!$D$5:$D$226,$A11,'Master Target List'!$O$5:$O$226,"Radar") -> 0 | H11: =SUM(B11:G11) -> 7 | I11: =COUNTIFS('Master Target List'!$D$5:$D$226,$A11,'Master Target List'!$R$5:$R$226,"<>v1") -> 1
A12: E-commerce / Consumer Tech / SaaS | B12: =COUNTIFS('Master Target List'!$D$5:$D$226,$A12,'Master Target List'!$O$5:$O$226,"High") -> 0 | C12: =COUNTIFS('Master Target List'!$D$5:$D$226,$A12,'Master Target List'!$O$5:$O$226,"Medium-High") -> 1 | D12: =COUNTIFS('Master Target List'!$D$5:$D$226,$A12,'Master Target List'!$O$5:$O$226,"Medium") -> 5 | E12: =COUNTIFS('Master Target List'!$D$5:$D$226,$A12,'Master Target List'!$O$5:$O$226,"Low-Medium") -> 4 | F12: =COUNTIFS('Master Target List'!$D$5:$D$226,$A12,'Master Target List'!$O$5:$O$226,"Low") -> 2 | G12: =COUNTIFS('Master Target List'!$D$5:$D$226,$A12,'Master Target List'!$O$5:$O$226,"Radar") -> 0 | H12: =SUM(B12:G12) -> 12 | I12: =COUNTIFS('Master Target List'!$D$5:$D$226,$A12,'Master Target List'!$R$5:$R$226,"<>v1") -> 9
A13: Banks & Insurers (Chinese) | B13: =COUNTIFS('Master Target List'!$D$5:$D$226,$A13,'Master Target List'!$O$5:$O$226,"High") -> 0 | C13: =COUNTIFS('Master Target List'!$D$5:$D$226,$A13,'Master Target List'!$O$5:$O$226,"Medium-High") -> 0 | D13: =COUNTIFS('Master Target List'!$D$5:$D$226,$A13,'Master Target List'!$O$5:$O$226,"Medium") -> 8 | E13: =COUNTIFS('Master Target List'!$D$5:$D$226,$A13,'Master Target List'!$O$5:$O$226,"Low-Medium") -> 1 | F13: =COUNTIFS('Master Target List'!$D$5:$D$226,$A13,'Master Target List'!$O$5:$O$226,"Low") -> 3 | G13: =COUNTIFS('Master Target List'!$D$5:$D$226,$A13,'Master Target List'!$O$5:$O$226,"Radar") -> 0 | H13: =SUM(B13:G13) -> 12 | I13: =COUNTIFS('Master Target List'!$D$5:$D$226,$A13,'Master Target List'!$R$5:$R$226,"<>v1") -> 6
A14: Brokerages / Asset Mgmt (Chinese) | B14: =COUNTIFS('Master Target List'!$D$5:$D$226,$A14,'Master Target List'!$O$5:$O$226,"High") -> 1 | C14: =COUNTIFS('Master Target List'!$D$5:$D$226,$A14,'Master Target List'!$O$5:$O$226,"Medium-High") -> 0 | D14: =COUNTIFS('Master Target List'!$D$5:$D$226,$A14,'Master Target List'!$O$5:$O$226,"Medium") -> 2 | E14: =COUNTIFS('Master Target List'!$D$5:$D$226,$A14,'Master Target List'!$O$5:$O$226,"Low-Medium") -> 4 | F14: =COUNTIFS('Master Target List'!$D$5:$D$226,$A14,'Master Target List'!$O$5:$O$226,"Low") -> 0 | G14: =COUNTIFS('Master Target List'!$D$5:$D$226,$A14,'Master Target List'!$O$5:$O$226,"Radar") -> 0 | H14: =SUM(B14:G14) -> 7 | I14: =COUNTIFS('Master Target List'!$D$5:$D$226,$A14,'Master Target List'!$R$5:$R$226,"<>v1") -> 2
A15: Quant / Trading Firms | B15: =COUNTIFS('Master Target List'!$D$5:$D$226,$A15,'Master Target List'!$O$5:$O$226,"High") -> 4 | C15: =COUNTIFS('Master Target List'!$D$5:$D$226,$A15,'Master Target List'!$O$5:$O$226,"Medium-High") -> 0 | D15: =COUNTIFS('Master Target List'!$D$5:$D$226,$A15,'Master Target List'!$O$5:$O$226,"Medium") -> 12 | E15: =COUNTIFS('Master Target List'!$D$5:$D$226,$A15,'Master Target List'!$O$5:$O$226,"Low-Medium") -> 5 | F15: =COUNTIFS('Master Target List'!$D$5:$D$226,$A15,'Master Target List'!$O$5:$O$226,"Low") -> 0 | G15: =COUNTIFS('Master Target List'!$D$5:$D$226,$A15,'Master Target List'!$O$5:$O$226,"Radar") -> 2 | H15: =SUM(B15:G15) -> 23 | I15: =COUNTIFS('Master Target List'!$D$5:$D$226,$A15,'Master Target List'!$R$5:$R$226,"<>v1") -> 16
... A20: Public Sector / GLC / Sovereign | B20: =COUNTIFS('Master Target List'!$D$5:$D$226,$A20,'Master Target List'!$O$5:$O$226,"High") -> 0 | C20: =COUNTIFS('Master Target List'!$D$5:$D$226,$A20,'Master Target List'!$O$5:$O$226,"Medium-High") -> 0 | D20: =COUNTIFS('Master Target List'!$D$5:$D$226,$A20,'Master Target List'!$O$5:$O$226,"Medium") -> 0 | E20: =COUNTIFS('Master Target List'!$D$5:$D$226,$A20,'Master Target List'!$O$5:$O$226,"Low-Medium") -> 2 | F20: =COUNTIFS('Master Target List'!$D$5:$D$226,$A20,'Master Target List'!$O$5:$O$226,"Low") -> 7 | G20: =COUNTIFS('Master Target List'!$D$5:$D$226,$A20,'Master Target List'!$O$5:$O$226,"Radar") -> 0 | H20: =SUM(B20:G20) -> 9 | I20: =COUNTIFS('Master Target List'!$D$5:$D$226,$A20,'Master Target List'!$R$5:$R$226,"<>v1") -> 7
A21: Total | B21: =SUM(B4:B20) -> 29 | C21: =SUM(C4:C20) -> 11 | D21: =SUM(D4:D20) -> 93 | E21: =SUM(E4:E20) -> 45 | F21: =SUM(F4:F20) -> 26 | G21: =SUM(G4:G20) -> 18 | H21: =SUM(H4:H20) -> 222 | I21: =SUM(I4:I20) -> 162
A23: Role direction | B23: Core need (●) | C23: Possible (○) | D23: Core — High / Med-High priority
A24: Data Engineer | B24: =COUNTIF('Master Target List'!$G$5:$G$226,"●") -> 158 | C24: =COUNTIF('Master Target List'!$G$5:$G$226,"○") -> 6 | D24: =COUNTIFS('Master Target List'!$G$5:$G$226,"●",'Master Target List'!$O$5:$O$226,"High")+COUNTIFS('Master Target List'!$G$5:$G$226,"●",'Master Target List'!$O$5:$O$226,"Medium-High") -> 32
A25: AI Governance | B25: =COUNTIF('Master Target List'!$H$5:$H$226,"●") -> 81 | C25: =COUNTIF('Master Target List'!$H$5:$H$226,"○") -> 11 | D25: =COUNTIFS('Master Target List'!$H$5:$H$226,"●",'Master Target List'!$O$5:$O$226,"High")+COUNTIFS('Master Target List'!$H$5:$H$226,"●",'Master Target List'!$O$5:$O$226,"Medium-High") -> 19
A26: AI Security | B26: =COUNTIF('Master Target List'!$I$5:$I$226,"●") -> 38 | C26: =COUNTIF('Master Target List'!$I$5:$I$226,"○") -> 16 | D26: =COUNTIFS('Master Target List'!$I$5:$I$226,"●",'Master Target List'!$O$5:$O$226,"High")+COUNTIFS('Master Target List'!$I$5:$I$226,"●",'Master Target List'!$O$5:$O$226,"Medium-High") -> 11
A27: AI Risk | B27: =COUNTIF('Master Target List'!$J$5:$J$226,"●") -> 67 | C27: =COUNTIF('Master Target List'!$J$5:$J$226,"○") -> 16 | D27: =COUNTIFS('Master Target List'!$J$5:$J$226,"●",'Master Target List'!$O$5:$O$226,"High")+COUNTIFS('Master Target List'!$J$5:$J$226,"●",'Master Target List'!$O$5:$O$226,"Medium-High") -> 12
A28: Software Engineer | B28: =COUNTIF('Master Target List'!$K$5:$K$226,"●") -> 100 | C28: =COUNTIF('Master Target List'!$K$5:$K$226,"○") -> 38 | D28: =COUNTIFS('Master Target List'!$K$5:$K$226,"●",'Master Target List'!$O$5:$O$226,"High")+COUNTIFS('Master Target List'!$K$5:$K$226,"●",'Master Target List'!$O$5:$O$226,"Medium-High") -> 22
A30: China Link type | B30: Meaning | C30: Count
A31: A | B31: Chinese HQ / SOE with SG entity | C31: =COUNTIF('Master Target List'!$E$5:$E$226,"A") -> 97
A32: B | B32: Chinese-founded, HQ'd or relocated to SG | C32: =COUNTIF('Master Target List'!$E$5:$E$226,"B") -> 26
A33: C | B33: Greater-China / Chinese-diaspora founders | C33: =COUNTIF('Master Target List'!$E$5:$E$226,"C") -> 26
A34: D | B34: Non-Chinese firm, China-origin tech leaders / TA (verify) | C34: =COUNTIF('Master Target List'!$E$5:$E$226,"D") -> 20
A35: E | B35: No specific China link — role fit only | C35: =COUNTIF('Master Target List'!$E$5:$E$226,"E") -> 53
A37: BD Status (pipeline) | B37: Count
A38: Not started | B38: =COUNTIF('Master Target List'!$T$5:$T$226,"Not started") -> 222
A39: Researching | B39: =COUNTIF('Master Target List'!$T$5:$T$226,"Researching") -> 0
A40: Contacted | B40: =COUNTIF('Master Target List'!$T$5:$T$226,"Contacted") -> 0
A41: Meeting set | B41: =COUNTIF('Master Target List'!$T$5:$T$226,"Meeting set") -> 0
A42: Proposal / terms | B42: =COUNTIF('Master Target List'!$T$5:$T$226,"Proposal / terms") -> 0
A43: Signed | B43: =COUNTIF('Master Target List'!$T$5:$T$226,"Signed") -> 0
A44: On hold | B44: =COUNTIF('Master Target List'!$T$5:$T$226,"On hold") -> 0
A45: Dead | B45: =COUNTIF('Master Target List'!$T$5:$T$226,"Dead") -> 0

Sheet First-Wave 30
A1: First-Wave Call List — 30 accounts to contact in the next 2-3 weeks
A2: Picked for: fresh signal (funding / relocation / new HQ / regulatory deadline) × Chinese-speaking decision makers × fit with your 5 role directions. Opening lines are drafts — adapt to each contact.
A4: # | B4: Company | C4: Why now | D4: Roles to pitch | E4: Draft opening line (中文 for Chinese-speaking HQ / English for local) | F4: BD Status | G4: Notes
A5: 1 | B5: Plaud | C5: New APAC HQ 16 Sep 2026; 100→150 hires; first overseas R&D hub | D5: AI / agent engineers, data scientists | E5: 看到Plaud新加坡APAC总部刚开业、团队9个月从10人到100人——剩下50个岗位里AI/Agent工程师最难招，我手上有在新加坡、做过LLM应用的候选人。 | F5: Not started
A6: 2 | B6: OneByZero (OBZ) | C6: US$20M Series A on 5 Oct 2026 | D6: Forward-deployed / data engineers, AI governance | E6: Congrats on the Series A — as you scale into Japan, I can help with forward-deployed and data engineers who have shipped enterprise AI in regulated industries. | F6: Not started
A7: 3 | B7: MiroMind (Shanda Group) | C7: AGI research consolidated in SG (Jan 2026); Shanghai staff relocating | D7: Research engineers, LLM infra, AI safety/verification | E7: 研究团队整体迁到新加坡后，一定有不愿搬的同事需要本地补位——我可以帮你们在新加坡本地补齐研究工程和LLM infra岗位。 | F7: Not started
A8: 4 | B8: Ropedia | C8: US$22M pre-Series A, physical-AI data infra | D8: Data engineers (core) | E8: Your product is data infrastructure — I specialise in data engineers and can bring 3-5 vetted profiles within two weeks. | F8: Not started
A9: 5 | B9: Moomoo (Futu) Singapore | C9: MAS AI Risk Guidelines (7 Oct 2026) + heavy data/AI | D9: AI Risk, AI Gov, data engineers | E9: MAS 10月7日刚发布AI风险管理指引，12个月过渡期——富途新加坡作为持牌机构需要AI治理/模型风险岗位，这类人才在市场上非常稀缺。 | F9: Not started
A10: 6 | B10: Tiger Brokers Singapore | C10: Same MAS deadline | D10: AI Risk, AI Gov, data engineers | E10: 同上：MAS AI风险指引的12个月过渡期，老虎新加坡需要提前布局AI治理和模型验证团队。 | F10: Not started
A11: 7 | B11: Ant International | C11: SG global HQ; AI SHIELD fraud AI; ANEXT bank under MAS rules | D11: AI Risk, AI Security, AI Gov | E11: Ant International 的 AI 风控与 ANEXT 银行的 MAS 合规双线都在扩——我专注 AI Risk / AI Security 这个细分，可以按业务线分别对接。 | F11: Not started
A12: 8 | B12: ByteDance Seed (SG lab) | C12: ~100 AI roles open (Feb 2026); SG is one of 3 lab sites | D12: Research engineers, AI safety, LLM infra | E12: Seed新加坡和TikTok是不同的招聘团队——我想单独聊Seed新加坡实验室的研究工程和AI安全岗位。 | F12: Not started
A13: 9 | B13: MiniMax | C13: SG subsidiaries confirmed; NUS/NTU AI recruiting | D13: AI Gov (overseas compliance), data, SWE | E13: 新加坡和美国是MiniMax最大的两个海外市场，本地合规和数据团队的搭建我可以帮忙，候选人中英文都能对接总部。 | F13: Not started
A14: 10 | B14: Zhipu AI (Z.ai) | C14: SG office confirmed; SEA sovereign-AI deals | D14: AI Gov, solutions/data engineers | E14: 智谱在东南亚做主权AI合作，新加坡团队需要懂本地监管(IMDA/AI Verify)的AI治理人才——这是我的专长方向。 | F14: Not started
A15: 11 | B15: ADVANCE.AI / Atome | C15: AI risk & KYC is the product; licensed lending | D15: AI Risk, AI Security (deepfake/fraud), DE | E15: 你们的核心就是AI风控——MAS新指引下模型风险和AI安全岗位需求会集中爆发，我可以先给2-3个对口候选人。 | F15: Not started
A16: 12 | B16: Simular | C16: First SG security hire (Jun 2026) | D16: AI / agent security engineers | E16: Your first security hire in SG will define the function — I can bring candidates who have secured agentic / LLM systems, not just generic appsec. | F16: Not started
... A34: 30 | B34: Pony.ai | C34: Apr 2026: approval for by-invite robotaxi rides in SG (final step before public service) | D34: AV safety (AI Risk), data, SWE | E34: 小马智行在新加坡已获批进入邀请制运营阶段，正式商业化前本地安全验证和数据工程团队需要扩充。 | F34: Not started

Sheet Search Playbook
A1: Search Playbook — how to find more Chinese-connected clients & verify 'D' rows
A3: FIND CHINESE TECH LEADERS (for 'D' rows)
A4: LinkedIn Sales Navigator — account filter | B4: Account HQ / location = Singapore; Headcount 50+; then Lead filter: Geography = Singapore, Seniority = Director/VP/CXO, Function = Engineering / IT / Risk
A5: …plus school filter | B5: School = Tsinghua, Peking, Zhejiang, Shanghai Jiao Tong, Fudan, USTC, Nanjing, Wuhan, HUST, Harbin IT, Beihang, Sun Yat-sen (also NUS/NTU with past company = ByteDance/Alibaba/Tencent/Baidu/Huawei)
A6: …plus language / past-company filter | B6: Profile language = Chinese, OR past company IN (ByteDance, Alibaba, Ant, Tencent, Baidu, Huawei, Meituan, JD, Pinduoduo, Kuaishou, NetEase, Xiaomi)
A7: Boolean (titles) — AI Gov / Risk | B7: ("AI governance" OR "responsible AI" OR "model risk" OR "AI risk" OR "model validation") AND (Singapore)
A8: Boolean (titles) — AI Security | B8: ("AI security" OR "LLM security" OR "AI red team" OR "adversarial" OR "trust and safety engineer") AND Singapore
A9: Find Chinese-speaking TA | B9: Title: ("talent acquisition" OR recruiter OR "HRBP") + Profile language = Chinese + Geography = Singapore → these are your warmest entry points
A10: FIND NEW CHINESE COMPANIES IN SG
A11: Chinese media keywords | B11: 36Kr / 晚点LatePost / 虎嗅 / 甲子光年 / 出海网: “新加坡 总部”, “出海 新加坡 招聘”, “迁往新加坡”, “新加坡 研发中心”, “AI 出海 新加坡”
A12: English media | B12: EDB newsroom (new HQ announcements), Business Times, Tech in Asia, e27, KrASIA 'Deals in brief', DealStreetAsia — search: 'China-founded' + 'Singapore headquarters'
A13: Company registry | B13: ACRA BizFile: search '[Chinese company English name] Pte. Ltd.' — new entities = expansion signal. Cross-check with HK IPO prospectuses (list SG subsidiaries — e.g. MiniMax, Zhipu)
A14: Regulator directories | B14: MAS Financial Institutions Directory: filter new licensees (CMS, MPI, DWB) — every licensed entity now falls under MAS AI Risk Guidelines
A15: Job-board signal | B15: MyCareersFuture.gov.sg: filter employer name; volume of new postings in last 30 days = hiring burst. LinkedIn Jobs: 'Singapore' + company + 'data engineer / AI'
A16: Communities & events | B16: SCCCI (新加坡中华总商会), China Enterprises Association Singapore (新加坡中资企业协会), 出海 founder WeChat groups, SuperAI Singapore, ATxSG, Singapore FinTech Festival (Nov), TOKEN2049 (Oct)
A17: Campus signal | B17: Chinese firms recruiting at NUS/NTU in 2026: Huawei, Alibaba, ByteDance, Trip.com, MiniMax — their lateral SG teams are growing too
A18: CADENCE
A19: Weekly | B19: Scan e27 / KrASIA / DealStreetAsia funding news; add any SG AI startup with a fresh round to Master list
A20: Monthly | B20: Re-check 'To verify' rows; move Radar → Medium when a SG entity or job post appears
A21: Quarterly | B21: ACRA + HK/US IPO filings for new SG subsidiaries of Chinese AI firms
A22: COMPLIANCE
A23: Data handling | B23: This list contains company-level information only. Collect individual contact details yourself via compliant channels (Sales Navigator, referrals, events) and respect PDPA.

Sheet v1 Strategy
A1: Singapore Headhunting BD Target List — Data Engineer & AI Governance
A2: Compiled from public industry research as of October 2026, for BD prioritization — not scraped from LinkedIn
A4: 1. Market Context (Why Now Is the Window)
A5: 1. MAS (Monetary Authority of Singapore) issued its AI Risk Management Guidelines on 7 Oct 2026, setting supervisory expectations for all regulated financial institutions (banks, insurers, asset managers, capital markets firms), with a roughly 12-month transition period (expected to end around Oct 2027). This means that over the next 12 months, banks and insurers will be setting up and expanding AI-governance-related roles (AI Ethics Officer, System Owner, AI risk validation specialists, etc.) — this is the core BD rationale for the AI Governance direction.
A6: 2. Project MindForge (a MAS-led consortium of 24 banks, insurers and capital markets firms) published its AI Risk Management Toolkit in March 2026 and the Agentic AI governance white paper (SAFR) in July 2026. These 24 institutions likely already have, or are building, internal AI governance teams and are worth checking one by one (the full list is in MAS's official announcement Annex A, which needs further verification).
A7: 3. On the Data Engineer side, Singapore remains Southeast Asia's tech/fintech hub — leading superapps, e-commerce platforms, quant trading firms and crypto exchanges continue to expand their data infrastructure teams. Most are MNCs or scale-ups with shorter decision chains, making them more approachable for agency recruiters.
A9: 2. Suggested BD Approach for Each Direction
A10: AI Governance direction:
A11: - Prioritize the Big Four consulting firms (EY/PwC/KPMG/Deloitte) first — they are themselves expanding their own AI governance consulting teams and are frequent, familiar users of agency recruiters, so conversion is faster; a good "foot in the door" client type.
A12: - Banks and insurers are the mid-to-long-term core market, but decision chains are longer and typically run through an HRBP/TA lead rather than the hiring manager directly; open with the "MAS 12-month transition" regulatory deadline to create urgency.
A13: - Insurance-sector AI governance build-out generally lags banks by 6-12 months and talent supply is scarcer — position candidates as "banking-background AI governance talent moving into insurance" as a differentiator.
A14: Data Engineer direction:
... A23: This list was compiled from public web research (MAS website, company career pages, industry media) — no LinkedIn personal data or contact information was scraped or compiled (privacy/platform compliance). Specific HR/TA contacts should be sourced and verified yourself via LinkedIn Sales Navigator, company websites, or your own network. All "BD signals" are a snapshot as of the research date (October 2026) — verify roles are still open before outreach. Entries marked "To verify" indicate that public research could not confirm specific details of the Singapore entity or team size — confirm directly before committing BD resources.

Sheet v1 Chinese-Background
A1: Chinese-Background Companies Target List (Singapore) — Data Engineer & AI Governance
A2: "To verify" = public research could not confirm Singapore entity/team size details; all other entries are backed by public job postings or industry reporting
A4: Category | B4: Company | C4: Sub-sector | D4: Role Focus | E4: Size / Stage | F4: BD Signal / Why Now | G4: Suggested BD Angle | H4: Priority | I4: Source
A5: Quant Funds / Hedge Funds | B5: High-Flyer Quant (幻方量化, DeepSeek's parent) | C5: Quant fund / AI | D5: Data Engineer, quant research infrastructure | E5: Top-tier, AUM ~$10B | F5: Amid tightening domestic regulation, top-tier Chinese quant funds are broadly accelerating overseas expansion (HK/Singapore); as DeepSeek's parent, its AI+quant hybrid talent needs are notable, but its Singapore entity/team is unconfirmed | G5: Lead with "quant + AI hybrid data engineering candidates"; proactively ask about its Singapore expansion plans | H5: High (pending confirmation) | I5: SCMP / public reporting combined; Singapore entity to verify
A6: Quant Funds / Hedge Funds | B6: Ubiquant (九坤投资) | C6: Quant fund | D6: Data Engineer | E6: Top-tier, AUM ~$11-13B | F6: Planning a US office in response to tightening regulation; likely considering Singapore/HK as an APAC hub in parallel | G6: Approach via industry contacts to learn its overseas expansion timeline | H6: Medium (pending confirmation) | I6: Public reporting combined; Singapore entity to verify
A7: Quant Funds / Hedge Funds | B7: Minghong Investment (明汯投资) | C7: Quant fund | D7: Data Engineer, quant infrastructure | E7: Top-tier, already has HK (Jupiter Research) and NY offices | F7: Exploring new strategy markets such as Japan and India; Singapore is a natural next step in its APAC expansion | G7: Ask directly about Singapore plans; build an early relationship | H7: Medium (pending confirmation) | I7: Public reporting combined
A8: Quant Funds / Hedge Funds | B8: MS Capital (Meridian & Saturn Capital) | C8: Quant fund | D8: Data Engineer | E8: Mid-size, confirmed Shanghai + Singapore offices | F8: Already offers China-strategy products to offshore investors; its Singapore office is a core hub for internationalization | G8: Confirmed Singapore entity — can approach directly; the highest-certainty target in this category | H8: High | I8: Industry reporting (confirmed Singapore office)
A9: Quant Funds / Hedge Funds | B9: Pinpoint Asset Management | C9: Quant fund | D9: Data Engineer | E9: Mid-size, HK/Singapore footprint | F9: Chinese-background quant fund founded by veteran hedge fund professionals, active APAC footprint | G9: Verify actual Singapore team size before committing BD resources | H9: Medium (to verify) | I9: Wikipedia / public reporting
A10: Quant Funds / Hedge Funds | B10: (Radar / long-tail) Post-2022 mainland quant funds expanding abroad | C10: Quant fund | D10: Data Engineer | E10: Long-tail, growing in number | F10: Regulatory tightening keeps driving new mainland quant funds (RMB 10bn+ AUM) to set up HK/Singapore teams — an emerging client pool worth scanning regularly | G10: Scan quarterly using keywords like "quant fund Singapore hiring" / "[fund name] Singapore office" | H10: Strategic / ongoing monitoring | I10: Industry trend synthesis
A11: Banks | B11: Bank of China Singapore | C11: State-owned bank | D11: Data Engineer + AI Governance (data governance) | E11: Large, long-term stable | F11: HQ continues its digital transformation; 2026 campus recruitment includes data analysis / frontier tech roles | G11: Long decision chain but stable long-term relationship; pursue via both campus and lateral hiring channels | H11: Medium | I11: BOC official 2026 campus recruitment announcement
A12: Banks | B12: ICBC Singapore | C12: State-owned bank | D12: Data Engineer + AI Governance | E12: Large, long-term stable | F12: Sector-wide digital transformation drives data/AI talent demand | G12: Same approach; emphasize native Mandarin communication advantage | H12: Medium | I12: Industry synthesis
A13: Banks | B13: China Construction Bank (CCB) Singapore | C13: State-owned bank | D13: Data Engineer + AI Governance | E13: Large, long-term stable | F13: Sector-wide digital transformation trend | G13: Same as above | H13: Medium | I13: Industry synthesis
A14: Banks | B14: Agricultural Bank of China (ABC) Singapore | C14: State-owned bank | D14: Data Engineer + AI Governance | E14: Large, long-term stable | F14: HQ has explicitly stated it is accelerating digital/intelligent transformation, deepening AI application and data potential | G14: Reference HQ's AI transformation strategy as a conversation opener | H14: Medium | I14: ABC public statements synthesis
A15: Banks | B15: Bank of Communications Singapore | C15: State-owned bank | D15: Data Engineer | E15: Mid-to-large, long-term stable | F15: Sector-wide digital transformation trend | G15: Same as above | H15: Low-Medium | I15: Industry synthesis
... A44: Outbound Startups / Cross-Border E-commerce / Consumer Brands | B44: (Long-tail blue ocean) Singapore-based Chinese cross-border e-commerce / DTC teams | C44: Cross-border e-commerce | D44: Data Engineer | E44: Long-tail, individual teams of 30-300 people | F44: Singapore hosts a large number of Chinese outbound e-commerce teams (ongoing ad-spend / data-analytics role demand) — a long-tail blue-ocean market for sustained outbound prospecting | G44: Build touchpoints in bulk via the Singapore Chinese Chamber of Commerce (SCCCI) and outbound-founder communities/events; package a standardized recruiting offer to convert at scale | H44: Medium (strategic) | I44: Industry observation synthesis

Sheet v1 AI Governance
A1: AI Governance Direction — Target Company List (Singapore, Supplementary / Non-Chinese-Background)
A3: Company | B3: Industry | C3: Role Focus | D3: BD Signal / Why Now | E3: Suggested BD Angle | F3: Priority | G3: Source
A4: DBS Bank | B4: Banking | C4: AI Governance (compliance) + AI Risk (technical) | D4: MAS issued its AI Risk Management Guidelines (7 Oct 2026) with a 12-month transition period; DBS has a Data & AI Risk team in its Risk Management Group, and separately hires AVP/VP AI Governance roles under Transformation & Data / Group COO | E4: Emphasize the urgency created by the compliance deadline; since DBS roles are split across two teams (Risk vs. Transformation), pitch a "unified cross-team candidate shortlist" angle | F4: High | G4: MAS website 2026-10-07 press release; DBS careers page
A5: UOB | B5: Banking | C5: AI Governance (Line 2 risk / technical) | D5: Set up a centralized Line 2 function, "AI & Data Risk Governance & Control," and is hiring a VP Advanced AI Risk Specialist to handle Agentic AI/GenAI risk assessment and validation methodology research | E5: Agentic AI governance is an extremely new niche with scarce talent; offer cross-industry candidates who are not purely banking-background but understand ML validation | F5: High | G5: UOB Workday careers page JR94868
A6: OCBC Bank | B6: Banking | C6: AI Governance (data-governance leaning) | D6: The Group Data Management Office (GDMO) is hiring an AI Governance Analyst (1-year contract), showing OCBC folds AI governance into its data governance structure, with team design still in flux | E6: The contract nature signals the team structure isn't fixed yet — pitch a "trial secondment, convert to permanent later" model to lower the client's decision threshold | F6: Medium | G6: OCBC careers page
A7: Standard Chartered | B7: Banking | C7: AI/ML emerging risk (senior) | D7: Hiring a Director, Strategic & Emerging Risks (AI & ML) under OTCR | E7: StanChart favors senior risk-background talent with AI knowledge; emphasize your pool of cross-industry hybrid-background candidates | F7: Medium | G7: Standard Chartered careers page
A8: HSBC (Singapore) | B8: Banking | C8: AI-related roles (ongoing hiring) | D8: Singapore office continues to post AI-related roles; building out a regionalized AI governance team | E8: Entry point: regional HQ AI governance team-building needs, build an early relationship | F8: Medium | G8: Indeed / HSBC careers page
A9: Prudential (PACS) | B9: Insurance | C9: AI Governance (compliance, full lifecycle) | D9: Hiring a Senior/Manager AI Governance role covering the full AI system lifecycle, from registration, risk assessment and approval through to monitoring and recertification | E9: Insurance-sector AI governance generally lags banking; talent supply is scarcer — pitch "banking-background AI governance talent moving into insurance" as a differentiator | F9: High | G9: Prudential Workday careers page
A10: AIA Singapore | B10: Insurance | C10: AI Governance (anticipatory positioning) | D10: No public AI Governance-specific role seen yet, but as a MAS-regulated insurance leader it will likely follow MindForge framework requirements | E10: Proactively reach out to ask about current team plans; build an early relationship ahead of its "first hire" | F10: Medium | G10: Industry analysis; recommend direct verification
A11: Great Eastern / Income Insurance | B11: Insurance | C11: AI Governance (anticipatory positioning) | D11: Same as above — expected to follow suit within 1-2 years under MAS regulatory pressure | E11: Same as above — early positioning plus regular follow-up | F11: Low-Medium | G11: Industry analysis; recommend direct verification
A12: EY Singapore | B12: Consulting | C12: AI Governance Risk Consulting | D12: Hiring a Senior Associate/Manager (AI Governance) - Risk Consulting, serving clients on AI governance/risk assessments | E12: The Big Four firms are themselves expanding AI governance consulting teams and are short-staffed — can be developed into a direct agency client, not just a source of client-leads | F12: High | G12: LinkedIn Jobs 4047834475
A13: PwC Singapore | B13: Consulting | C13: AI Governance / regulated industries | D13: Investing $1B globally in AI capability, focused on governance consulting for regulated industries (finance/public sector) | E13: Large-scale investment typically comes with ongoing hiring needs; lead with "regulated-industry AI governance specialists" | F13: High | G13: Industry reporting synthesis
A14: KPMG Singapore | B14: Consulting | C14: Responsible AI | D14: KPMG has made responsible AI a core consulting practice; its Digital Village focuses on serving MNCs and GLCs | E14: Entry point: staffing gaps on governance delivery projects for MNC/GLC clients | F14: Medium | G14: Industry reporting synthesis
... A17: Remaining Project MindForge consortium members (24 banks/insurers/capital markets firms) | B17: Multi-sector finance | C17: AI Governance (all types) | D17: MAS's official announcement Annex A lists the full 24 participating institutions (this research could not retrieve the complete list); these institutions likely already have, or are building, AI governance teams | E17: Obtain the official MAS press release Annex A to confirm the full list, and screen the institutions not yet covered one by one | F17: Follow-up | G17: MAS 2026-03 press release (Annex A needs further verification)

Sheet v1 Data Engineer
A1: Data Engineer Direction — Target Company List (Singapore, Supplementary / Non-Chinese-Background)
A3: Company | B3: Industry | C3: Role Focus | D3: BD Signal / Why Now | E3: Suggested BD Angle | F3: Priority | G3: Source
A4: Grab | B4: Ride-hailing / fintech super-app | C4: Data Engineer (multiple levels, platform/infrastructure) | D4: Singapore R&D centre, 5,001-10,000 employees, continuous large-scale hiring | E4: SEA's largest super-app, large and high-turnover data teams — a good candidate for a long-term, steady client relationship | F4: High | G4: Glassdoor / Grab careers page
A5: Sea Group / Shopee | B5: E-commerce | C5: Data Engineer + AI infrastructure | D5: New AI Centre of Excellence launched in July 2026; data infrastructure roles (OLAP, etc.) continuously open | E5: New CoE launches typically bring sudden team-building needs — a BD entry window | F5: High | G5: Industry reporting, hiredeveloper.sg
A6: ByteDance / TikTok (Singapore) | B6: Content tech | C6: Data Engineer (big data / data lake) | D6: Multiple Singapore roles open: Big Data Engineer (Libra), Data Ingestion Engineer, Data Lake-related roles | E6: Fast-moving, high-volume hiring at this MNC — good fit for a standing-search agreement | F6: High | G6: Glassdoor ByteDance careers page
A7: Razer | B7: Gaming / fintech | C7: Data Engineer | D7: Singapore HQ, both gaming and payments lines drive data needs | E7: Gaming-analytics roles are highly competitive — lead with your passive-candidate sourcing advantage | F7: Medium | G7: Public careers page
A8: GoodNotes | B8: SaaS / productivity software | C8: Data Engineer | D8: Singapore-HQ'd growth-stage unicorn, engineering team continuing to expand | E8: Small HR team at a startup — more willing to use an agency to speed up hiring | F8: Medium | G8: Public careers page
A9: Coinhako | B9: Crypto exchange | C9: Data Engineer | D9: Locally licensed exchange, continuing to build data infrastructure | E9: Licensed entity may also need AI/data-governance talent — pitch both directions as a bundle | F9: Medium | G9: Glassdoor careers page
A10: Qube Research & Technologies | B10: Quant trading | C10: Data Engineer (quant infrastructure) | D10: Singapore office continuously hiring data/quant infrastructure roles | E10: Quant firms pay well with strict hiring bars — lead with precision scarce-candidate matching | F10: High | G10: Glassdoor careers page
A11: DRW | B11: Quant trading | C11: Data Engineer | D11: Singapore office hiring data engineers | E11: Same as above — high pay, high bar, small candidate pool | F11: Medium | G11: Glassdoor careers page
A12: Paradex | B12: Crypto derivatives | C12: Senior/Principal Data Engineer, Quant Developer | D12: Multiple active data engineering and quant development roles open in Singapore | E12: An emerging crypto derivatives platform in expansion mode, short decision chain, fast BD conversion | F12: Medium | G12: Public careers page
A13: Bullet | B13: Crypto HFT | C13: Data Engineer | D13: Founded by the former Zeta Markets team, backed by top crypto funds including Electric Capital, Jump Capital, Race Capital, and Wintermute | E13: A newly funded early-stage team, expanding without a mature HR setup yet — high value for agency involvement | F13: High | G13: Industry reporting synthesis
A14: Applied Materials (Singapore) | B14: Semiconductor | C14: Data Engineer (manufacturing data) | D14: Singapore continuously posting data engineer roles | E14: Traditional large-company hiring cycles are longer — good fit for a long-term relationship play | F14: Low-Medium | G14: Glassdoor / Jobstreet
... A17: Argus Media | B17: Commodities data | C17: Data Engineer | D17: Singapore office hiring data engineers; data/information services are its core business | E17: Data is the core business and hiring bar is high — good fit for deep specialization in this niche | F17: Medium | G17: Glassdoor careers page
